Workbook

Sheet Calculator
A1: Needs/Assets | B1: Financial needs in retirement | C1: Tax-Deferred (401k / IRA / Pension) | D1: No-Tax (Roth 401k/IRA & HSA) | E1: Taxable (Stock Investments) | F1: Other Investments (Real Estate, Crypto, etc.) | G1: Growth rate (return) before retirement | H1: 0.15
A2: Current year / Retirement age | B2: =(YEAR(today())) -> 2026 | C2: =H7 -> 56 | D2: =C2 -> 56 | E2: =C2 -> 56 | F2: =C2 -> 56 | G2: Loan rate (if borrowed for expenses) | H2: 0.06
A3: Retirement start | B3: =H8+C2 -> 2029 | G3: Growth rate (return) during retirement | H3: =H1*0.6 -> 0.09
A4: Years left for retirement | B4: =(B3-B2) -> 3 | C4: =B4 -> 3 | D4: =C4 -> 3 | E4: =B4 -> 3 | F4: =C4 -> 3 | G4: Capital gains & gividends blended tax rate | H4: 0.1
A5: Annual retirement expenses in today's $s | B5: =IF(H7<65,(Expenses!C12)*12,(Expenses!B12)*12) -> 132000 | G5: Income tax rate during retirement | H5: 0.2
G6: Inflation | H6: 0.04
G7: Retirement age | H7: 56
A8: Annual expenses at retirement - after tax | B8: =FV(H6,B4,0,-B5,0) -> 148482.05 | G8: Birth year | H8: 1973
A9: Annual income needed from savings - pre tax | B9: =(B8)*(1+H5) -> 178178.46 | G9: Retirement distributions start age | H9: 60
A10: Principal needed for retirement - 4% rule | B10: =(B9*25) -> 4454461.4 | G10: Social security benefit start age | H10: 62
A11: Total needed at retirement | B11: =SUM(B10) -> 4454461.4 | G11: Estimated SS income - annual per person | H11: 20000
A12: Growth rate (update cell H1) | C12: =H1 -> 0.15 | D12: =H1 -> 0.15 | E12: =H1 -> 0.15 | F12: =H1 -> 0.15 | G12: Other recurring income at start of retirement - annual | H12: 0
A13: Current savings | B13: =SUM(C13:F13) -> 3335000 | C13: =Accounts!C23 -> 1868000 | D13: =Accounts!C24 -> 168000 | E13: =Accounts!C25 -> 873000 | F13: =Accounts!C26 -> 426000 | G13: Other Income before retirement distributions - annual | H13: 0
A14: Current contributions - annual | C14: 23000 | D14: 6500 | E14: 20000 | F14: 0 | G14: % withdrawn in retirement | H14: 0.04
A15: Employer match | C15: 15000 | D15: 0 | E15: 0 | F15: 0 | G15: Age of asset transfer to kids | H15: 80
A16: Additional catch up contributions - annual | C16: 7000 | D16: 1000 | E16: 0 | F16: 0 | G16: Total money needed for special expenses | H16: =SUM(Details!N4:N88) -> 1150000
A17: Total contributions - annual | C17: =(C14+C15+C16)*H17 -> 90000 | D17: =(D14+D15+D16)*H17 -> 15000 | E17: =(E14+E15+E16)*H17 -> 40000 | F17: =(F14+F15+F16) -> 0 | G17: Contribution multiplier (number of earners) | H17: 2
A18: Savings with total contributions | C18: =FV(C12, C4, -C17,-C13, 0) -> 3153519.5 | D18: =FV(D12, D4, -D17,-D13, 0) -> 307594.5 | E18: =FV(E12, E4, -E17,-E13, 0) -> 1466623.9 | F18: =FV(F12, F4, -F17,-F13, 0) -> 647892.75 | G18: Borrow for special expenses (Y/N) | H18: N
A19: Cumulative assets at retirement | C19: =C18 -> 3153519.5 | D19: =C19+D18 -> 3461114 | E19: =D19+E18 -> 4927737.9 | F19: =E19+F18 -> 5575630.6 | G19: Funds will be available until age | H19: {=IFERROR(INDEX(Details!$B$4:Details!$B$107,MATCH(TRUE,Details!$S$4:Details!$S$107<0,0))-1,"Forever")} -> Forever
A20: Gap/Excess at retirement | B20: =-B11 -> -4454461.4 | C20: =B20+C18 -> -1300941.9 | D20: =C20+D18 -> -993347.44 | E20: =D20+E18 -> 473276.43 | F20: =E20+F18 -> 1121169.2 | G20: Money left to transfer to kids | H20: {=INDEX(Details!$S$4:Details!$S$107,MATCH(TRUE,Details!$B$4:Details!$B$107=H15,0))} -> 15899099
A22: Change assumptions in these cells. Dont change other cells.

Sheet Details
A1: Year | B1: Age | C1: Event | D1: SSA Income | E1: 401K Distribution | F1: Roth Distribution | G1: Investment Income | H1: Other Investments Income | I1: Other recurring incone | J1: Total Income (after-tax)* | K1: Total Income | L1: After Tax Income | M1: Living Expenses | N1: Special Expenses | O1: Total Expenses | P1: Gap/Excess | Q1: Cumilative Liability | R1: Assets Remaining | S1: Networth | T1: 401k Balance | U1: Roth Balance | V1: Investment Balance | W1: Other Investments Balance | X1: Unqualified Income | Y1: Standard Deduction | Z1: Tax Free Income | AA1: Taxable Income | AB1: Tax | AC1: Tax as a % of total income | AD1: Test
A2: 2020 | B2: =A2-Calculator!$H$8 -> 47
A3: 2021 | B3: =A3-Calculator!$H$8 -> 48
A4: 2022 | B4: =A4-Calculator!$H$8 -> 49 | D4: =IF(D3=0,IF(B4>=Calculator!$H$10,Calculator!$H$11,0)*Calculator!$H$17,D3*(1+Calculator!$H$6)) -> 0 | E4: =IF(B4>=Calculator!$H$9,T3*Calculator!$H$14,0) -> 0 | F4: =IF(B4>=Calculator!$H$9,U3*Calculator!$H$14,0) -> 0 | G4: =IF(B4>=Calculator!$H$7,V3*Calculator!$H$14,0) -> 0 | H4: =IF(B4>=Calculator!$H$7,IF(W3<=0,0,W3*Calculator!$H$14),0) -> 0 | I4: =IF(I3=0,IF(B4>=Calculator!$H$7,Calculator!$H$12,0),I3*(1+Calculator!$H$6)) -> 0 | J4: =(D4*0.85+E4+H4+I4)*(1-Calculator!$H$5)+D4*0.15+(G4)*(1-Calculator!$H$4)+F4 -> 0 | K4: =D4+E4+F4+G4+H4+I4 -> 0 | L4: =K4-AB4 -> 0 | M4: =IF(B4=Calculator!$H$7,Calculator!$B$8,M3*(1+Calculator!$H$6)) -> 0 | O4: =M4+N4 -> 0 | P4: =L4-O4 -> 0 | Q4: =IF(Calculator!$H$18="Y",Q3+IF(Q3<0,Q3*Calculator!$H$2,Q3*Calculator!$H$3)+P4,0) -> 0 | R4: =T4+U4+V4+W4 -> 1492825.2 | S4: =Q4+R4 -> 1492825.2 | T4: =IF(B4>=Calculator!$H$7,T3*(1+Calculator!$H$3)-E4,FV(Calculator!$H$1,B4+Calculator!$H$8-Calculator!$B$2, -Calculator!$C$17,-Calculator!$C$13)) -> 811087.01 | U4: =IF(B4>=Calculator!$H$7,U3*(1+Calculator!$H$3)-F4,FV(Calculator!$H$1,B4+Calculator!$H$8-Calculator!$B$2, -Calculator!$D$17,-Calculator!$D$13)) -> 53229.87 | V4: =IF(B4>=Calculator!$H$7,V3*(1+Calculator!$H$3)-G4,FV(Calculator!$H$1,B4+Calculator!$H$8-Calculator!$B$2, -Calculator!$E$17,-Calculator!$E$13)) -> 384941.45 | W4: =IF(B4>=Calculator!$H$7,W3*(1+Calculator!$H$3)-H4,FV(Calculator!$H$1,B4+Calculator!$H$8-Calculator!$B$2, -Calculator!$F$17,-Calculator!$F$13))+P4 -> 243566.88 | X4: =D4*0.85+E4+G4+H4 -> 0 | Y4: 26000 | Z4: =IF(X4>0,D4*0.15+F4+Y4,0) -> 0 | AA4: =X4-Z4 -> 0 | AB4: =AA4*Calculator!$H$5 -> 0
A5: 2023 | B5: =A5-Calculator!$H$8 -> 50 | C5: Cars | D5: =IF(D4=0,IF(B5>=Calculator!$H$10,Calculator!$H$11,0)*Calculator!$H$17,D4*(1+Calculator!$H$6)) -> 0 | E5: =IF(B5>=Calculator!$H$9,T4*Calculator!$H$14,0) -> 0 | F5: =IF(B5>=Calculator!$H$9,U4*Calculator!$H$14,0) -> 0 | G5: =IF(B5>=Calculator!$H$7,V4*Calculator!$H$14,0) -> 0 | H5: =IF(B5>=Calculator!$H$7,IF(W4<=0,0,W4*Calculator!$H$14),0) -> 0 | I5: =IF(I4=0,IF(B5>=Calculator!$H$7,Calculator!$H$12,0),I4*(1+Calculator!$H$6)) -> 0 | J5: =(D5*0.85+E5+H5+I5)*(1-Calculator!$H$5)+D5*0.15+(G5)*(1-Calculator!$H$4)+F5 -> 0 | K5: =D5+E5+F5+G5+H5+I5 -> 0 | L5: =K5-AB5 -> 0 | M5: =IF(B5=Calculator!$C$2,Calculator!$B$8,M4*(1+Calculator!$H$6)) -> 0 | N5: 0 | O5: =M5+N5 -> 0 | P5: =L5-O5 -> 0 | Q5: =IF(Calculator!$H$18="Y",Q4+IF(Q4<0,Q4*Calculator!$H$2,Q4*Calculator!$H$3)+P5,0) -> 0 | R5: =T5+U5+V5+W5 -> 1861749 | S5: =Q5+R5 -> 1861749 | T5: =IF(B5>=Calculator!$H$7,T4*(1+Calculator!$H$3)-E5,FV(Calculator!$H$1,B5+Calculator!$H$8-Calculator!$B$2, -Calculator!$C$17,-Calculator!$C$13)) -> 1022750.1 | U5: =IF(B5>=Calculator!$H$7,U4*(1+Calculator!$H$3)-F5,FV(Calculator!$H$1,B5+Calculator!$H$8-Calculator!$B$2, -Calculator!$D$17,-Calculator!$D$13)) -> 76214.35 | V5: =IF(B5>=Calculator!$H$7,V4*(1+Calculator!$H$3)-G5,FV(Calculator!$H$1,B5+Calculator!$H$8-Calculator!$B$2, -Calculator!$E$17,-Calculator!$E$13)) -> 482682.67 | W5: =IF(B5>=Calculator!$H$7,W4*(1+Calculator!$H$3)-H5,FV(Calculator!$H$1,B5+Calculator!$H$8-Calculator!$B$2, -Calculator!$F$17,-Calculator!$F$13))+P5 -> 280101.91 | X5: =D5*0.85+E5+G5+H5 -> 0 | Y5: =Y4*(1+Calculator!$H$6) -> 27040 | Z5: =IF(X5>0,D5*0.15+F5+Y5,0) -> 0 | AA5: =X5-Z5 -> 0 | AB5: =AA5*Calculator!$H$5 -> 0 | AC5: =IF((X5+Z5)=0,0,AB5/(X5+Z5)*100) -> 0 | AD5: =T5-T4 -> 211663.05
A6: 2024 | B6: =A6-Calculator!$H$8 -> 51 | C6: Gifts4Nieces&Nephews1 | D6: =IF(D5=0,IF(B6>=Calculator!$H$10,Calculator!$H$11,0)*Calculator!$H$17,D5*(1+Calculator!$H$6)) -> 0 | E6: =IF(B6>=Calculator!$H$9,T5*Calculator!$H$14,0) -> 0 | F6: =IF(B6>=Calculator!$H$9,U5*Calculator!$H$14,0) -> 0 | G6: =IF(B6>=Calculator!$H$7,V5*Calculator!$H$14,0) -> 0 | H6: =IF(B6>=Calculator!$H$7,IF(W5<=0,0,W5*Calculator!$H$14),0) -> 0 | I6: =IF(I5=0,IF(B6>=Calculator!$H$7,Calculator!$H$12,0),I5*(1+Calculator!$H$6)) -> 0 | J6: =(D6*0.85+E6+H6+I6)*(1-Calculator!$H$5)+D6*0.15+(G6)*(1-Calculator!$H$4)+F6 -> 0 | K6: =D6+E6+F6+G6+H6+I6 -> 0 | L6: =K6-AB6 -> 0 | M6: =IF(B6=Calculator!$C$2,Calculator!$B$8,M5*(1+Calculator!$H$6)) -> 0 | N6: 0 | O6: =M6+N6 -> 0 | P6: =L6-O6 -> 0 | Q6: =IF(Calculator!$H$18="Y",Q5+IF(Q5<0,Q5*Calculator!$H$2,Q5*Calculator!$H$3)+P6,0) -> 0 | R6: =T6+U6+V6+W6 -> 2286011.3 | S6: =Q6+R6 -> 2286011.3 | T6: =IF(B6>=Calculator!$H$7,T5*(1+Calculator!$H$3)-E6,FV(Calculator!$H$1,B6+Calculator!$H$8-Calculator!$B$2, -Calculator!$C$17,-Calculator!$C$13)) -> 1266162.6 | U6: =IF(B6>=Calculator!$H$7,U5*(1+Calculator!$H$3)-F6,FV(Calculator!$H$1,B6+Calculator!$H$8-Calculator!$B$2, -Calculator!$D$17,-Calculator!$D$13)) -> 102646.5 | V6: =IF(B6>=Calculator!$H$7,V5*(1+Calculator!$H$3)-G6,FV(Calculator!$H$1,B6+Calculator!$H$8-Calculator!$B$2, -Calculator!$E$17,-Calculator!$E$13)) -> 595085.07 | W6: =IF(B6>=Calculator!$H$7,W5*(1+Calculator!$H$3)-H6,FV(Calculator!$H$1,B6+Calculator!$H$8-Calculator!$B$2, -Calculator!$F$17,-Calculator!$F$13))+P6 -> 322117.2 | X6: =D6+E6+G6+H6 -> 0 | Y6: =Y5*(1+Calculator!$H$6) -> 28121.6 | Z6: =IF(X6>0,D6*0.15+F6+Y6,0) -> 0 | AA6: =X6-Z6 -> 0 | AB6: =AA6*Calculator!$H$5 -> 0 | AC6: =IF((X6+Z6)=0,0,AB6/(X6+Z6)*100) -> 0 | AD6: =T6-T5 -> 243412.51
A7: 2025 | B7: =A7-Calculator!$H$8 -> 52 | C7: College 1 | D7: =IF(D6=0,IF(B7>=Calculator!$H$10,Calculator!$H$11,0)*Calculator!$H$17,D6*(1+Calculator!$H$6)) -> 0 | E7: =IF(B7>=Calculator!$H$9,T6*Calculator!$H$14,0) -> 0 | F7: =IF(B7>=Calculator!$H$9,U6*Calculator!$H$14,0) -> 0 | G7: =IF(B7>=Calculator!$H$7,V6*Calculator!$H$14,0) -> 0 | H7: =IF(B7>=Calculator!$H$7,IF(W6<=0,0,W6*Calculator!$H$14),0) -> 0 | I7: =IF(I6=0,IF(B7>=Calculator!$H$7,Calculator!$H$12,0),I6*(1+Calculator!$H$6)) -> 0 | J7: =(D7*0.85+E7+H7+I7)*(1-Calculator!$H$5)+D7*0.15+(G7)*(1-Calculator!$H$4)+F7 -> 0 | K7: =D7+E7+F7+G7+H7+I7 -> 0 | L7: =K7-AB7 -> 0 | M7: =IF(B7=Calculator!$C$2,Calculator!$B$8,M6*(1+Calculator!$H$6)) -> 0 | N7: 0 | O7: =M7+N7 -> 0 | P7: =L7-O7 -> 0 | Q7: =IF(Calculator!$H$18="Y",Q6+IF(Q6<0,Q6*Calculator!$H$2,Q6*Calculator!$H$3)+P7,0) -> 0 | R7: =T7+U7+V7+W7 -> 2773913 | S7: =Q7+R7 -> 2773913 | T7: =IF(B7>=Calculator!$H$7,T6*(1+Calculator!$H$3)-E7,FV(Calculator!$H$1,B7+Calculator!$H$8-Calculator!$B$2, -Calculator!$C$17,-Calculator!$C$13)) -> 1546087 | U7: =IF(B7>=Calculator!$H$7,U6*(1+Calculator!$H$3)-F7,FV(Calculator!$H$1,B7+Calculator!$H$8-Calculator!$B$2, -Calculator!$D$17,-Calculator!$D$13)) -> 133043.48 | V7: =IF(B7>=Calculator!$H$7,V6*(1+Calculator!$H$3)-G7,FV(Calculator!$H$1,B7+Calculator!$H$8-Calculator!$B$2, -Calculator!$E$17,-Calculator!$E$13)) -> 724347.83 | W7: =IF(B7>=Calculator!$H$7,W6*(1+Calculator!$H$3)-H7,FV(Calculator!$H$1,B7+Calculator!$H$8-Calculator!$B$2, -Calculator!$F$17,-Calculator!$F$13))+P7 -> 370434.78 | X7: =D7+E7+G7+H7 -> 0 | Y7: =Y6*(1+Calculator!$H$6) -> 29246.464 | Z7: =IF(X7>0,D7*0.15+F7+Y7,0) -> 0 | AA7: =X7-Z7 -> 0 | AB7: =AA7*Calculator!$H$5 -> 0 | AC7: =IF((X7+Z7)=0,0,AB7/(X7+Z7)*100) -> 0 | AD7: =T7-T6 -> 279924.39
A8: 2026 | B8: =A8-Calculator!$H$8 -> 53 | D8: =IF(D7=0,IF(B8>=Calculator!$H$10,Calculator!$H$11,0)*Calculator!$H$17,D7*(1+Calculator!$H$6)) -> 0 | E8: =IF(B8>=Calculator!$H$9,T7*Calculator!$H$14,0) -> 0 | F8: =IF(B8>=Calculator!$H$9,U7*Calculator!$H$14,0) -> 0 | G8: =IF(B8>=Calculator!$H$7,V7*Calculator!$H$14,0) -> 0 | H8: =IF(B8>=Calculator!$H$7,IF(W7<=0,0,W7*Calculator!$H$14),0) -> 0 | I8: =IF(I7=0,IF(B8>=Calculator!$H$7,Calculator!$H$12,0),I7*(1+Calculator!$H$6)) -> 0 | J8: =(D8*0.85+E8+H8+I8)*(1-Calculator!$H$5)+D8*0.15+(G8)*(1-Calculator!$H$4)+F8 -> 0 | K8: =D8+E8+F8+G8+H8+I8 -> 0 | L8: =K8-AB8 -> 0 | M8: =IF(B8=Calculator!$C$2,Calculator!$B$8,M7*(1+Calculator!$H$6)) -> 0 | O8: =M8+N8 -> 0 | P8: =L8-O8 -> 0 | Q8: =IF(Calculator!$H$18="Y",Q7+IF(Q7<0,Q7*Calculator!$H$2,Q7*Calculator!$H$3)+P8,0) -> 0 | R8: =T8+U8+V8+W8 -> 3335000 | S8: =Q8+R8 -> 3335000 | T8: =IF(B8>=Calculator!$H$7,T7*(1+Calculator!$H$3)-E8,FV(Calculator!$H$1,B8+Calculator!$H$8-Calculator!$B$2, -Calculator!$C$17,-Calculator!$C$13)) -> 1868000 | U8: =IF(B8>=Calculator!$H$7,U7*(1+Calculator!$H$3)-F8,FV(Calculator!$H$1,B8+Calculator!$H$8-Calculator!$B$2, -Calculator!$D$17,-Calculator!$D$13)) -> 168000 | V8: =IF(B8>=Calculator!$H$7,V7*(1+Calculator!$H$3)-G8,FV(Calculator!$H$1,B8+Calculator!$H$8-Calculator!$B$2, -Calculator!$E$17,-Calculator!$E$13)) -> 873000 | W8: =IF(B8>=Calculator!$H$7,W7*(1+Calculator!$H$3)-H8,FV(Calculator!$H$1,B8+Calculator!$H$8-Calculator!$B$2, -Calculator!$F$17,-Calculator!$F$13))+P8 -> 426000 | X8: =D8+E8+G8+H8 -> 0 | Y8: =Y7*(1+Calculator!$H$6) -> 30416.323 | Z8: =IF(X8>0,D8*0.15+F8+Y8,0) -> 0 | AA8: =X8-Z8 -> 0 | AB8: =AA8*Calculator!$H$5 -> 0 | AC8: =IF((X8+Z8)=0,0,AB8/(X8+Z8)*100) -> 0 | AD8: =T8-T7 -> 321913.04
A9: 2027 | B9: =A9-Calculator!$H$8 -> 54 | C9: Gifts4Nieces&Nephews2 | D9: =IF(D8=0,IF(B9>=Calculator!$H$10,Calculator!$H$11,0)*Calculator!$H$17,D8*(1+Calculator!$H$6)) -> 0 | E9: =IF(B9>=Calculator!$H$9,T8*Calculator!$H$14,0) -> 0 | F9: =IF(B9>=Calculator!$H$9,U8*Calculator!$H$14,0) -> 0 | G9: =IF(B9>=Calculator!$H$7,V8*Calculator!$H$14,0) -> 0 | H9: =IF(B9>=Calculator!$H$7,IF(W8<=0,0,W8*Calculator!$H$14),0) -> 0 | I9: =IF(I8=0,IF(B9>=Calculator!$H$7,Calculator!$H$12,0),I8*(1+Calculator!$H$6)) -> 0 | J9: =(D9*0.85+E9+H9+I9)*(1-Calculator!$H$5)+D9*0.15+(G9)*(1-Calculator!$H$4)+F9 -> 0 | K9: =D9+E9+F9+G9+H9+I9 -> 0 | L9: =K9-AB9 -> 0 | M9: =IF(B9=Calculator!$C$2,Calculator!$B$8,M8*(1+Calculator!$H$6)) -> 0 | N9: 100000 | O9: =M9+N9 -> 100000 | P9: =L9-O9 -> -100000 | Q9: =IF(Calculator!$H$18="Y",Q8+IF(Q8<0,Q8*Calculator!$H$2,Q8*Calculator!$H$3)+P9,0) -> 0 | R9: =T9+U9+V9+W9 -> 3880250 | S9: =Q9+R9 -> 3880250 | T9: =IF(B9>=Calculator!$H$7,T8*(1+Calculator!$H$3)-E9,FV(Calculator!$H$1,B9+Calculator!$H$8-Calculator!$B$2, -Calculator!$C$17,-Calculator!$C$13)) -> 2238200 | U9: =IF(B9>=Calculator!$H$7,U8*(1+Calculator!$H$3)-F9,FV(Calculator!$H$1,B9+Calculator!$H$8-Calculator!$B$2, -Calculator!$D$17,-Calculator!$D$13)) -> 208200 | V9: =IF(B9>=Calculator!$H$7,V8*(1+Calculator!$H$3)-G9,FV(Calculator!$H$1,B9+Calculator!$H$8-Calculator!$B$2, -Calculator!$E$17,-Calculator!$E$13)) -> 1043950 | W9: =IF(B9>=Calculator!$H$7,W8*(1+Calculator!$H$3)-H9,FV(Calculator!$H$1,B9+Calculator!$H$8-Calculator!$B$2, -Calculator!$F$17,-Calculator!$F$13))+P9 -> 389900 | X9: =D9+E9+G9+H9 -> 0 | Y9: =Y8*(1+Calculator!$H$6) -> 31632.975 | Z9: =IF(X9>0,D9*0.15+F9+Y9,0) -> 0 | AA9: =X9-Z9 -> 0 | AB9: =AA9*Calculator!$H$5 -> 0 | AC9: =IF((X9+Z9)=0,0,AB9/(X9+Z9)*100) -> 0 | AD9: =T9-T8 -> 370200
A10: 2028 | B10: =A10-Calculator!$H$8 -> 55 | C10: Prasee Annuity | D10: =IF(D9=0,IF(B10>=Calculator!$H$10,Calculator!$H$11,0)*Calculator!$H$17,D9*(1+Calculator!$H$6)) -> 0 | E10: =IF(B10>=Calculator!$H$9,T9*Calculator!$H$14,0) -> 0 | F10: =IF(B10>=Calculator!$H$9,U9*Calculator!$H$14,0) -> 0 | G10: =IF(B10>=Calculator!$H$7,V9*Calculator!$H$14,0) -> 0 | H10: =IF(B10>=Calculator!$H$7,IF(W9<=0,0,W9*Calculator!$H$14),0) -> 0 | I10: =IF(I9=0,IF(B10>=Calculator!$H$7,Calculator!$H$12,0),I9*(1+Calculator!$H$6)) -> 0 | J10: =(D10*0.85+E10+H10+I10)*(1-Calculator!$H$5)+D10*0.15+(G10)*(1-Calculator!$H$4)+F10 -> 0 | K10: =D10+E10+F10+G10+H10+I10 -> 0 | L10: =K10-AB10 -> 0 | M10: =IF(B10=Calculator!$C$2,Calculator!$B$8,M9*(1+Calculator!$H$6)) -> 0 | N10: 0 | O10: =M10+N10 -> 0 | P10: =L10-O10 -> 0 | Q10: =IF(Calculator!$H$18="Y",Q9+IF(Q9<0,Q9*Calculator!$H$2,Q9*Calculator!$H$3)+P10,0) -> 0 | R10: =T10+U10+V10+W10 -> 4722287.5 | S10: =Q10+R10 -> 4722287.5 | T10: =IF(B10>=Calculator!$H$7,T9*(1+Calculator!$H$3)-E10,FV(Calculator!$H$1,B10+Calculator!$H$8-Calculator!$B$2, -Calculator!$C$17,-Calculator!$C$13)) -> 2663930 | U10: =IF(B10>=Calculator!$H$7,U9*(1+Calculator!$H$3)-F10,FV(Calculator!$H$1,B10+Calculator!$H$8-Calculator!$B$2, -Calculator!$D$17,-Calculator!$D$13)) -> 254430 | V10: =IF(B10>=Calculator!$H$7,V9*(1+Calculator!$H$3)-G10,FV(Calculator!$H$1,B10+Calculator!$H$8-Calculator!$B$2, -Calculator!$E$17,-Calculator!$E$13)) -> 1240542.5 | W10: =IF(B10>=Calculator!$H$7,W9*(1+Calculator!$H$3)-H10,FV(Calculator!$H$1,B10+Calculator!$H$8-Calculator!$B$2, -Calculator!$F$17,-Calculator!$F$13))+P10 -> 563385 | X10: =D10+E10+G10+H10 -> 0 | Y10: =Y9*(1+Calculator!$H$6) -> 32898.294 | Z10: =IF(X10>0,D10*0.15+F10+Y10,0) -> 0 | AA10: =X10-Z10 -> 0 | AB10: =AA10*Calculator!$H$5 -> 0 | AC10: =IF((X10+Z10)=0,0,AB10/(X10+Z10)*100) -> 0 | AD10: =T10-T9 -> 425730
A11: 2029 | B11: =A11-Calculator!$H$8 -> 56 | C11: Wedding 1 | D11: =IF(D10=0,IF(B11>=Calculator!$H$10,Calculator!$H$11,0)*Calculator!$H$17,D10*(1+Calculator!$H$6)) -> 0 | E11: =IF(B11>=Calculator!$H$9,T10*Calculator!$H$14,0) -> 0 | F11: =IF(B11>=Calculator!$H$9,U10*Calculator!$H$14,0) -> 0 | G11: =IF(B11>=Calculator!$H$7,V10*Calculator!$H$14,0) -> 49621.7 | H11: =IF(B11>=Calculator!$H$7,IF(W10<=0,0,W10*Calculator!$H$14),0) -> 22535.4 | I11: =IF(I10=0,IF(B11>=Calculator!$H$7,Calculator!$H$12,0),I10*(1+Calculator!$H$6)) -> 0 | J11: =(D11*0.85+E11+H11+I11)*(1-Calculator!$H$5)+D11*0.15+(G11)*(1-Calculator!$H$4)+F11 -> 62687.85 | K11: =D11+E11+F11+G11+H11+I11 -> 72157.1 | L11: =K11-AB11 -> 64568.525 | M11: =IF(B11=Calculator!$C$2,Calculator!$B$8,M10*(1+Calculator!$H$6)) -> 148482.05 | N11: 200000 | O11: =M11+N11 -> 348482.05 | P11: =L11-O11 -> -283913.52 | Q11: =IF(Calculator!$H$18="Y",Q10+IF(Q10<0,Q10*Calculator!$H$2,Q10*Calculator!$H$3)+P11,0) -> 0 | R11: =T11+U11+V11+W11 -> 4791222.8 | S11: =Q11+R11 -> 4791222.8 | T11: =IF(B11>=Calculator!$H$7,T10*(1+Calculator!$H$3)-E11,FV(Calculator!$H$1,B11+Calculator!$H$8-Calculator!$B$2, -Calculator!$C$17,-Calculator!$C$13)) -> 2903683.7 | U11: =IF(B11>=Calculator!$H$7,U10*(1+Calculator!$H$3)-F11,FV(Calculator!$H$1,B11+Calculator!$H$8-Calculator!$B$2, -Calculator!$D$17,-Calculator!$D$13)) -> 277328.7 | V11: =IF(B11>=Calculator!$H$7,V10*(1+Calculator!$H$3)-G11,FV(Calculator!$H$1,B11+Calculator!$H$8-Calculator!$B$2, -Calculator!$E$17,-Calculator!$E$13)) -> 1302569.6 | W11: =IF(B11>=Calculator!$H$7,W10*(1+Calculator!$H$3)-H11,FV(Calculator!$H$1,B11+Calculator!$H$8-Calculator!$B$2, -Calculator!$F$17,-Calculator!$F$13))+P11 -> 307640.73 | X11: =D11+E11+G11+H11 -> 72157.1 | Y11: =Y10*(1+Calculator!$H$6) -> 34214.226 | Z11: =IF(X11>0,D11*0.15+F11+Y11,0) -> 34214.226 | AA11: =X11-Z11 -> 37942.874 | AB11: =AA11*Calculator!$H$5 -> 7588.5747 | AC11: =IF((X11+Z11)=0,0,AB11/(X11+Z11)*100) -> 7.1340417 | AD11: =T11-T10 -> 239753.7
A12: 2030 | B12: =A12-Calculator!$H$8 -> 57 | C12: Jewelery and stuff | D12: =IF(D11=0,IF(B12>=Calculator!$H$10,Calculator!$H$11,0)*Calculator!$H$17,D11*(1+Calculator!$H$6)) -> 0 | E12: =IF(B12>=Calculator!$H$9,T11*Calculator!$H$14,0) -> 0 | F12: =IF(B12>=Calculator!$H$9,U11*Calculator!$H$14,0) -> 0 | G12: =IF(B12>=Calculator!$H$7,V11*Calculator!$H$14,0) -> 52102.785 | H12: =IF(B12>=Calculator!$H$7,IF(W11<=0,0,W11*Calculator!$H$14),0) -> 12305.629 | I12: =IF(I11=0,IF(B12>=Calculator!$H$7,Calculator!$H$12,0),I11*(1+Calculator!$H$6)) -> 0 | J12: =(D12*0.85+E12+H12+I12)*(1-Calculator!$H$5)+D12*0.15+(G12)*(1-Calculator!$H$4)+F12 -> 56737.01 | K12: =D12+E12+F12+G12+H12+I12 -> 64408.414 | L12: =K12-AB12 -> 58643.29 | M12: =IF(B12=Calculator!$C$2,Calculator!$B$8,M11*(1+Calculator!$H$6)) -> 154421.33 | N12: 200000 | O12: =M12+N12 -> 354421.33 | P12: =L12-O12 -> -295778.04 | Q12: =IF(Calculator!$H$18="Y",Q11+IF(Q11<0,Q11*Calculator!$H$2,Q11*Calculator!$H$3)+P12,0) -> 0 | R12: =T12+U12+V12+W12 -> 4862246.3 | S12: =Q12+R12 -> 4862246.3 | T12: =IF(B12>=Calculator!$H$7,T11*(1+Calculator!$H$3)-E12,FV(Calculator!$H$1,B12+Calculator!$H$8-Calculator!$B$2, -Calculator!$C$17,-Calculator!$C$13)) -> 3165015.2 | U12: =IF(B12>=Calculator!$H$7,U11*(1+Calculator!$H$3)-F12,FV(Calculator!$H$1,B12+Calculator!$H$8-Calculator!$B$2, -Calculator!$D$17,-Calculator!$D$13)) -> 302288.28 | V12: =IF(B12>=Calculator!$H$7,V11*(1+Calculator!$H$3)-G12,FV(Calculator!$H$1,B12+Calculator!$H$8-Calculator!$B$2, -Calculator!$E$17,-Calculator!$E$13)) -> 1367698.1 | W12: =IF(B12>=Calculator!$H$7,W11*(1+Calculator!$H$3)-H12,FV(Calculator!$H$1,B12+Calculator!$H$8-Calculator!$B$2, -Calculator!$F$17,-Calculator!$F$13))+P12 -> 27244.724 | X12: =D12+E12+G12+H12 -> 64408.414 | Y12: =Y11*(1+Calculator!$H$6) -> 35582.795 | Z12: =IF(X12>0,D12*0.15+F12+Y12,0) -> 35582.795 | AA12: =X12-Z12 -> 28825.619 | AB12: =AA12*Calculator!$H$5 -> 5765.1238 | AC12: =IF((X12+Z12)=0,0,AB12/(X12+Z12)*100) -> 5.7656306 | AD12: =T12-T11 -> 261331.53
A13: 2031 | B13: =A13-Calculator!$H$8 -> 58 | C13: Gifts4Nieces&Nephews3 | D13: =IF(D12=0,IF(B13>=Calculator!$H$10,Calculator!$H$11,0)*Calculator!$H$17,D12*(1+Calculator!$H$6)) -> 0 | E13: =IF(B13>=Calculator!$H$9,T12*Calculator!$H$14,0) -> 0 | F13: =IF(B13>=Calculator!$H$9,U12*Calculator!$H$14,0) -> 0 | G13: =IF(B13>=Calculator!$H$7,V12*Calculator!$H$14,0) -> 54707.924 | H13: =IF(B13>=Calculator!$H$7,IF(W12<=0,0,W12*Calculator!$H$14),0) -> 1089.789 | I13: =IF(I12=0,IF(B13>=Calculator!$H$7,Calculator!$H$12,0),I12*(1+Calculator!$H$6)) -> 0 | J13: =(D13*0.85+E13+H13+I13)*(1-Calculator!$H$5)+D13*0.15+(G13)*(1-Calculator!$H$4)+F13 -> 50108.963 | K13: =D13+E13+F13+G13+H13+I13 -> 55797.713 | L13: =K13-AB13 -> 52039.392 | M13: =IF(B13=Calculator!$C$2,Calculator!$B$8,M12*(1+Calculator!$H$6)) -> 160598.18 | N13: 50000 | O13: =M13+N13 -> 210598.18 | P13: =L13-O13 -> -158558.79 | Q13: =IF(Calculator!$H$18="Y",Q12+IF(Q12<0,Q12*Calculator!$H$2,Q12*Calculator!$H$3)+P13,0) -> 0 | R13: =T13+U13+V13+W13 -> 5085492 | S13: =Q13+R13 -> 5085492 | T13: =IF(B13>=Calculator!$H$7,T12*(1+Calculator!$H$3)-E13,FV(Calculator!$H$1,B13+Calculator!$H$8-Calculator!$B$2, -Calculator!$C$17,-Calculator!$C$13)) -> 3449866.6 | U13: =IF(B13>=Calculator!$H$7,U12*(1+Calculator!$H$3)-F13,FV(Calculator!$H$1,B13+Calculator!$H$8-Calculator!$B$2, -Calculator!$D$17,-Calculator!$D$13)) -> 329494.23 | V13: =IF(B13>=Calculator!$H$7,V12*(1+Calculator!$H$3)-G13,FV(Calculator!$H$1,B13+Calculator!$H$8-Calculator!$B$2, -Calculator!$E$17,-Calculator!$E$13)) -> 1436083 | W13: =IF(B13>=Calculator!$H$7,W12*(1+Calculator!$H$3)-H13,FV(Calculator!$H$1,B13+Calculator!$H$8-Calculator!$B$2, -Calculator!$F$17,-Calculator!$F$13))+P13 -> -129951.83 | X13: =D13+E13+G13+H13 -> 55797.713 | Y13: =Y12*(1+Calculator!$H$6) -> 37006.107 | Z13: =IF(X13>0,D13*0.15+F13+Y13,0) -> 37006.107 | AA13: =X13-Z13 -> 18791.606 | AB13: =AA13*Calculator!$H$5 -> 3758.3212 | AC13: =IF((X13+Z13)=0,0,AB13/(X13+Z13)*100) -> 4.0497484 | AD13: =T13-T12 -> 284851.37
A14: 2032 | B14: =A14-Calculator!$H$8 -> 59 | D14: =IF(D13=0,IF(B14>=Calculator!$H$10,Calculator!$H$11,0)*Calculator!$H$17,D13*(1+Calculator!$H$6)) -> 0 | E14: =IF(B14>=Calculator!$H$9,T13*Calculator!$H$14,0) -> 0 | F14: =IF(B14>=Calculator!$H$9,U13*Calculator!$H$14,0) -> 0 | G14: =IF(B14>=Calculator!$H$7,V13*Calculator!$H$14,0) -> 57443.32 | H14: =IF(B14>=Calculator!$H$7,IF(W13<=0,0,W13*Calculator!$H$14),0) -> 0 | I14: =IF(I13=0,IF(B14>=Calculator!$H$7,Calculator!$H$12,0),I13*(1+Calculator!$H$6)) -> 0 | J14: =(D14*0.85+E14+H14+I14)*(1-Calculator!$H$5)+D14*0.15+(G14)*(1-Calculator!$H$4)+F14 -> 51698.988 | K14: =D14+E14+F14+G14+H14+I14 -> 57443.32 | L14: =K14-AB14 -> 53651.927 | M14: =IF(B14=Calculator!$C$2,Calculator!$B$8,M13*(1+Calculator!$H$6)) -> 167022.11 | O14: =M14+N14 -> 167022.11 | P14: =L14-O14 -> -113370.18 | Q14: =IF(Calculator!$H$18="Y",Q13+IF(Q13<0,Q13*Calculator!$H$2,Q13*Calculator!$H$3)+P14,0) -> 0 | R14: =T14+U14+V14+W14 -> 5372372.8 | S14: =Q14+R14 -> 5372372.8 | T14: =IF(B14>=Calculator!$H$7,T13*(1+Calculator!$H$3)-E14,FV(Calculator!$H$1,B14+Calculator!$H$8-Calculator!$B$2, -Calculator!$C$17,-Calculator!$C$13)) -> 3760354.6 | U14: =IF(B14>=Calculator!$H$7,U13*(1+Calculator!$H$3)-F14,FV(Calculator!$H$1,B14+Calculator!$H$8-Calculator!$B$2, -Calculator!$D$17,-Calculator!$D$13)) -> 359148.71 | V14: =IF(B14>=Calculator!$H$7,V13*(1+Calculator!$H$3)-G14,FV(Calculator!$H$1,B14+Calculator!$H$8-Calculator!$B$2, -Calculator!$E$17,-Calculator!$E$13)) -> 1507887.2 | W14: =IF(B14>=Calculator!$H$7,W13*(1+Calculator!$H$3)-H14,FV(Calculator!$H$1,B14+Calculator!$H$8-Calculator!$B$2, -Calculator!$F$17,-Calculator!$F$13))+P14 -> -255017.68 | X14: =D14+E14+G14+H14 -> 57443.32 | Y14: =Y13*(1+Calculator!$H$6) -> 38486.351 | Z14: =IF(X14>0,D14*0.15+F14+Y14,0) -> 38486.351 | AA14: =X14-Z14 -> 18956.969 | AB14: =AA14*Calculator!$H$5 -> 3791.3938 | AC14: =IF((X14+Z14)=0,0,AB14/(X14+Z14)*100) -> 3.9522639 | AD14: =T14-T13 -> 310487.99
A15: 2033 | B15: =A15-Calculator!$H$8 -> 60 | C15: Colege 2 | D15: =IF(D14=0,IF(B15>=Calculator!$H$10,Calculator!$H$11,0)*Calculator!$H$17,D14*(1+Calculator!$H$6)) -> 0 | E15: =IF(B15>=Calculator!$H$9,T14*Calculator!$H$14,0) -> 150414.18 | F15: =IF(B15>=Calculator!$H$9,U14*Calculator!$H$14,0) -> 14365.948 | G15: =IF(B15>=Calculator!$H$7,V14*Calculator!$H$14,0) -> 60315.486 | H15: =IF(B15>=Calculator!$H$7,IF(W14<=0,0,W14*Calculator!$H$14),0) -> 0 | I15: =IF(I14=0,IF(B15>=Calculator!$H$7,Calculator!$H$12,0),I14*(1+Calculator!$H$6)) -> 0 | J15: =(D15*0.85+E15+H15+I15)*(1-Calculator!$H$5)+D15*0.15+(G15)*(1-Calculator!$H$4)+F15 -> 188981.23 | K15: =D15+E15+F15+G15+H15+I15 -> 225095.62 | L15: =K15-AB15 -> 193828.04 | M15: =IF(B15=Calculator!$C$2,Calculator!$B$8,M14*(1+Calculator!$H$6)) -> 173702.99 | N15: 300000 | O15: =M15+N15 -> 473702.99 | P15: =L15-O15 -> -279874.96 | Q15: =IF(Calculator!$H$18="Y",Q14+IF(Q14<0,Q14*Calculator!$H$2,Q14*Calculator!$H$3)+P15,0) -> 0 | R15: =T15+U15+V15+W15 -> 5350915.8 | S15: =Q15+R15 -> 5350915.8 | T15: =IF(B15>=Calculator!$H$7,T14*(1+Calculator!$H$3)-E15,FV(Calculator!$H$1,B15+Calculator!$H$8-Calculator!$B$2, -Calculator!$C$17,-Calculator!$C$13)) -> 3948372.3 | U15: =IF(B15>=Calculator!$H$7,U14*(1+Calculator!$H$3)-F15,FV(Calculator!$H$1,B15+Calculator!$H$8-Calculator!$B$2, -Calculator!$D$17,-Calculator!$D$13)) -> 377106.14 | V15: =IF(B15>=Calculator!$H$7,V14*(1+Calculator!$H$3)-G15,FV(Calculator!$H$1,B15+Calculator!$H$8-Calculator!$B$2, -Calculator!$E$17,-Calculator!$E$13)) -> 1583281.5 | W15: =IF(B15>=Calculator!$H$7,W14*(1+Calculator!$H$3)-H15,FV(Calculator!$H$1,B15+Calculator!$H$8-Calculator!$B$2, -Calculator!$F$17,-Calculator!$F$13))+P15 -> -557844.23 | X15: =D15+E15+G15+H15 -> 210729.67 | Y15: =Y14*(1+Calculator!$H$6) -> 40025.805 | Z15: =IF(X15>0,D15*0.15+F15+Y15,0) -> 54391.754 | AA15: =X15-Z15 -> 156337.92 | AB15: =AA15*Calculator!$H$5 -> 31267.583 | AC15: =IF((X15+Z15)=0,0,AB15/(X15+Z15)*100) -> 11.793684 | AD15: =T15-T14 -> 188017.73
A16: 2034 | B16: =A16-Calculator!$H$8 -> 61 | D16: =IF(D15=0,IF(B16>=Calculator!$H$10,Calculator!$H$11,0)*Calculator!$H$17,D15*(1+Calculator!$H$6)) -> 0 | E16: =IF(B16>=Calculator!$H$9,T15*Calculator!$H$14,0) -> 157934.89 | F16: =IF(B16>=Calculator!$H$9,U15*Calculator!$H$14,0) -> 15084.246 | G16: =IF(B16>=Calculator!$H$7,V15*Calculator!$H$14,0) -> 63331.261 | H16: =IF(B16>=Calculator!$H$7,IF(W15<=0,0,W15*Calculator!$H$14),0) -> 0 | I16: =IF(I15=0,IF(B16>=Calculator!$H$7,Calculator!$H$12,0),I15*(1+Calculator!$H$6)) -> 0 | J16: =(D16*0.85+E16+H16+I16)*(1-Calculator!$H$5)+D16*0.15+(G16)*(1-Calculator!$H$4)+F16 -> 198430.3 | K16: =D16+E16+F16+G16+H16+I16 -> 236350.4 | L16: =K16-AB16 -> 203439.39 | M16: =IF(B16=Calculator!$C$2,Calculator!$B$8,M15*(1+Calculator!$H$6)) -> 180651.11 | O16: =M16+N16 -> 180651.11 | P16: =L16-O16 -> 22788.271 | Q16: =IF(Calculator!$H$18="Y",Q15+IF(Q15<0,Q15*Calculator!$H$2,Q15*Calculator!$H$3)+P16,0) -> 0 | R16: =T16+U16+V16+W16 -> 5618936.1 | S16: =Q16+R16 -> 5618936.1 | T16: =IF(B16>=Calculator!$H$7,T15*(1+Calculator!$H$3)-E16,FV(Calculator!$H$1,B16+Calculator!$H$8-Calculator!$B$2, -Calculator!$C$17,-Calculator!$C$13)) -> 4145790.9 | U16: =IF(B16>=Calculator!$H$7,U15*(1+Calculator!$H$3)-F16,FV(Calculator!$H$1,B16+Calculator!$H$8-Calculator!$B$2, -Calculator!$D$17,-Calculator!$D$13)) -> 395961.45 | V16: =IF(B16>=Calculator!$H$7,V15*(1+Calculator!$H$3)-G16,FV(Calculator!$H$1,B16+Calculator!$H$8-Calculator!$B$2, -Calculator!$E$17,-Calculator!$E$13)) -> 1662445.6 | W16: =IF(B16>=Calculator!$H$7,W15*(1+Calculator!$H$3)-H16,FV(Calculator!$H$1,B16+Calculator!$H$8-Calculator!$B$2, -Calculator!$F$17,-Calculator!$F$13))+P16 -> -585261.94 | X16: =D16+E16+G16+H16 -> 221266.15 | Y16: =Y15*(1+Calculator!$H$6) -> 41626.838 | Z16: =IF(X16>0,D16*0.15+F16+Y16,0) -> 56711.083 | AA16: =X16-Z16 -> 164555.07 | AB16: =AA16*Calculator!$H$5 -> 32911.014 | AC16: =IF((X16+Z16)=0,0,AB16/(X16+Z16)*100) -> 11.839464 | AD16: =T16-T15 -> 197418.62
A17: 2035 | B17: =A17-Calculator!$H$8 -> 62 | D17: =IF(D16=0,IF(B17>=Calculator!$H$10,Calculator!$H$11,0)*Calculator!$H$17,D16*(1+Calculator!$H$6)) -> 40000 | E17: =IF(B17>=Calculator!$H$9,T16*Calculator!$H$14,0) -> 165831.64 | F17: =IF(B17>=Calculator!$H$9,U16*Calculator!$H$14,0) -> 15838.458 | G17: =IF(B17>=Calculator!$H$7,V16*Calculator!$H$14,0) -> 66497.824 | H17: =IF(B17>=Calculator!$H$7,IF(W16<=0,0,W16*Calculator!$H$14),0) -> 0 | I17: =IF(I16=0,IF(B17>=Calculator!$H$7,Calculator!$H$12,0),I16*(1+Calculator!$H$6)) -> 0 | J17: =(D17*0.85+E17+H17+I17)*(1-Calculator!$H$5)+D17*0.15+(G17)*(1-Calculator!$H$4)+F17 -> 241551.81 | K17: =D17+E17+F17+G17+H17+I17 -> 288167.92 | L17: =K17-AB17 -> 246728.1 | M17: =IF(B17=Calculator!$C$2,Calculator!$B$8,M16*(1+Calculator!$H$6)) -> 187877.16 | O17: =M17+N17 -> 187877.16 | P17: =L17-O17 -> 58850.942 | Q17: =IF(Calculator!$H$18="Y",Q16+IF(Q16<0,Q16*Calculator!$H$2,Q16*Calculator!$H$3)+P17,0) -> 0 | R17: =T17+U17+V17+W17 -> 5935323.3 | S17: =Q17+R17 -> 5935323.3 | T17: =IF(B17>=Calculator!$H$7,T16*(1+Calculator!$H$3)-E17,FV(Calculator!$H$1,B17+Calculator!$H$8-Calculator!$B$2, -Calculator!$C$17,-Calculator!$C$13)) -> 4353080.5 | U17: =IF(B17>=Calculator!$H$7,U16*(1+Calculator!$H$3)-F17,FV(Calculator!$H$1,B17+Calculator!$H$8-Calculator!$B$2, -Calculator!$D$17,-Calculator!$D$13)) -> 415759.52 | V17: =IF(B17>=Calculator!$H$7,V16*(1+Calculator!$H$3)-G17,FV(Calculator!$H$1,B17+Calculator!$H$8-Calculator!$B$2, -Calculator!$E$17,-Calculator!$E$13)) -> 1745567.9 | W17: =IF(B17>=Calculator!$H$7,W16*(1+Calculator!$H$3)-H17,FV(Calculator!$H$1,B17+Calculator!$H$8-Calculator!$B$2, -Calculator!$F$17,-Calculator!$F$13))+P17 -> -579084.57 | X17: =D17+E17+G17+H17 -> 272329.46 | Y17: =Y16*(1+Calculator!$H$6) -> 43291.911 | Z17: =IF(X17>0,D17*0.15+F17+Y17,0) -> 65130.369 | AA17: =X17-Z17 -> 207199.09 | AB17: =AA17*Calculator!$H$5 -> 41439.818 | AC17: =IF((X17+Z17)=0,0,AB17/(X17+Z17)*100) -> 12.279926 | AD17: =T17-T16 -> 207289.55
A18: 2036 | B18: =A18-Calculator!$H$8 -> 63 | C18: Wedding 2 | D18: =IF(D17=0,IF(B18>=Calculator!$H$10,Calculator!$H$11,0)*Calculator!$H$17,D17*(1+Calculator!$H$6)) -> 41600 | E18: =IF(B18>=Calculator!$H$9,T17*Calculator!$H$14,0) -> 174123.22 | F18: =IF(B18>=Calculator!$H$9,U17*Calculator!$H$14,0) -> 16630.381 | G18: =IF(B18>=Calculator!$H$7,V17*Calculator!$H$14,0) -> 69822.715 | H18: =IF(B18>=Calculator!$H$7,IF(W17<=0,0,W17*Calculator!$H$14),0) -> 0 | I18: =IF(I17=0,IF(B18>=Calculator!$H$7,Calculator!$H$12,0),I17*(1+Calculator!$H$6)) -> 0 | J18: =(D18*0.85+E18+H18+I18)*(1-Calculator!$H$5)+D18*0.15+(G18)*(1-Calculator!$H$4)+F18 -> 253297.4 | K18: =D18+E18+F18+G18+H18+I18 -> 302176.32 | L18: =K18-AB18 -> 258645.92 | M18: =IF(B18=Calculator!$C$2,Calculator!$B$8,M17*(1+Calculator!$H$6)) -> 195392.25 | N18: 300000 | O18: =M18+N18 -> 495392.25 | P18: =L18-O18 -> -236746.32 | Q18: =IF(Calculator!$H$18="Y",Q17+IF(Q17<0,Q17*Calculator!$H$2,Q17*Calculator!$H$3)+P18,0) -> 0 | R18: =T18+U18+V18+W18 -> 5972179.8 | S18: =Q18+R18 -> 5972179.8 | T18: =IF(B18>=Calculator!$H$7,T17*(1+Calculator!$H$3)-E18,FV(Calculator!$H$1,B18+Calculator!$H$8-Calculator!$B$2, -Calculator!$C$17,-Calculator!$C$13)) -> 4570734.5 | U18: =IF(B18>=Calculator!$H$7,U17*(1+Calculator!$H$3)-F18,FV(Calculator!$H$1,B18+Calculator!$H$8-Calculator!$B$2, -Calculator!$D$17,-Calculator!$D$13)) -> 436547.5 | V18: =IF(B18>=Calculator!$H$7,V17*(1+Calculator!$H$3)-G18,FV(Calculator!$H$1,B18+Calculator!$H$8-Calculator!$B$2, -Calculator!$E$17,-Calculator!$E$13)) -> 1832846.3 | W18: =IF(B18>=Calculator!$H$7,W17*(1+Calculator!$H$3)-H18,FV(Calculator!$H$1,B18+Calculator!$H$8-Calculator!$B$2, -Calculator!$F$17,-Calculator!$F$13))+P18 -> -867948.51 | X18: =D18+E18+G18+H18 -> 285545.93 | Y18: =Y17*(1+Calculator!$H$6) -> 45023.588 | Z18: =IF(X18>0,D18*0.15+F18+Y18,0) -> 67893.969 | AA18: =X18-Z18 -> 217651.97 | AB18: =AA18*Calculator!$H$5 -> 43530.393 | AC18: =IF((X18+Z18)=0,0,AB18/(X18+Z18)*100) -> 12.316208 | AD18: =T18-T17 -> 217654.02
A19: 2037 | B19: =A19-Calculator!$H$8 -> 64 | D19: =IF(D18=0,IF(B19>=Calculator!$H$10,Calculator!$H$11,0)*Calculator!$H$17,D18*(1+Calculator!$H$6)) -> 43264 | E19: =IF(B19>=Calculator!$H$9,T18*Calculator!$H$14,0) -> 182829.38 | F19: =IF(B19>=Calculator!$H$9,U18*Calculator!$H$14,0) -> 17461.9 | G19: =IF(B19>=Calculator!$H$7,V18*Calculator!$H$14,0) -> 73313.851 | H19: =IF(B19>=Calculator!$H$7,IF(W18<=0,0,W18*Calculator!$H$14),0) -> 0 | I19: =IF(I18=0,IF(B19>=Calculator!$H$7,Calculator!$H$12,0),I18*(1+Calculator!$H$6)) -> 0 | J19: =(D19*0.85+E19+H19+I19)*(1-Calculator!$H$5)+D19*0.15+(G19)*(1-Calculator!$H$4)+F19 -> 265616.99 | K19: =D19+E19+F19+G19+H19+I19 -> 316869.13 | L19: =K19-AB19 -> 271142.89 | M19: =IF(B19=Calculator!$C$2,Calculator!$B$8,M18*(1+Calculator!$H$6)) -> 203207.94 | O19: =M19+N19 -> 203207.94 | P19: =L19-O19 -> 67934.956 | Q19: =IF(Calculator!$H$18="Y",Q18+IF(Q18<0,Q18*Calculator!$H$2,Q18*Calculator!$H$3)+P19,0) -> 0 | R19: =T19+U19+V19+W19 -> 6304005.8 | S19: =Q19+R19 -> 6304005.8 | T19: =IF(B19>=Calculator!$H$7,T18*(1+Calculator!$H$3)-E19,FV(Calculator!$H$1,B19+Calculator!$H$8-Calculator!$B$2, -Calculator!$C$17,-Calculator!$C$13)) -> 4799271.2 | U19: =IF(B19>=Calculator!$H$7,U18*(1+Calculator!$H$3)-F19,FV(Calculator!$H$1,B19+Calculator!$H$8-Calculator!$B$2, -Calculator!$D$17,-Calculator!$D$13)) -> 458374.88 | V19: =IF(B19>=Calculator!$H$7,V18*(1+Calculator!$H$3)-G19,FV(Calculator!$H$1,B19+Calculator!$H$8-Calculator!$B$2, -Calculator!$E$17,-Calculator!$E$13)) -> 1924488.6 | W19: =IF(B19>=Calculator!$H$7,W18*(1+Calculator!$H$3)-H19,FV(Calculator!$H$1,B19+Calculator!$H$8-Calculator!$B$2, -Calculator!$F$17,-Calculator!$F$13))+P19 -> -878128.92 | X19: =D19+E19+G19+H19 -> 299407.23 | Y19: =Y18*(1+Calculator!$H$6) -> 46824.531 | Z19: =IF(X19>0,D19*0.15+F19+Y19,0) -> 70776.031 | AA19: =X19-Z19 -> 228631.2 | AB19: =AA19*Calculator!$H$5 -> 45726.24 | AC19: =IF((X19+Z19)=0,0,AB19/(X19+Z19)*100) -> 12.352325 | AD19: =T19-T18 -> 228536.73
A20: 2038 | B20: =A20-Calculator!$H$8 -> 65 | D20: =IF(D19=0,IF(B20>=Calculator!$H$10,Calculator!$H$11,0)*Calculator!$H$17,D19*(1+Calculator!$H$6)) -> 44994.56 | E20: =IF(B20>=Calculator!$H$9,T19*Calculator!$H$14,0) -> 191970.85 | F20: =IF(B20>=Calculator!$H$9,U19*Calculator!$H$14,0) -> 18334.995 | G20: =IF(B20>=Calculator!$H$7,V19*Calculator!$H$14,0) -> 76979.543 | H20: =IF(B20>=Calculator!$H$7,IF(W19<=0,0,W19*Calculator!$H$14),0) -> 0 | I20: =IF(I19=0,IF(B20>=Calculator!$H$7,Calculator!$H$12,0),I19*(1+Calculator!$H$6)) -> 0 | J20: =(D20*0.85+E20+H20+I20)*(1-Calculator!$H$5)+D20*0.15+(G20)*(1-Calculator!$H$4)+F20 -> 278538.75 | K20: =D20+E20+F20+G20+H20+I20 -> 332279.95 | L20: =K20-AB20 -> 284247.3 | M20: =IF(B20=Calculator!$C$2,Calculator!$B$8,M19*(1+Calculator!$H$6)) -> 211336.25 | O20: =M20+N20 -> 211336.25 | P20: =L20-O20 -> 72911.043 | Q20: =IF(Calculator!$H$18="Y",Q19+IF(Q19<0,Q19*Calculator!$H$2,Q19*Calculator!$H$3)+P20,0) -> 0 | R20: =T20+U20+V20+W20 -> 6656992 | S20: =Q20+R20 -> 6656992 | T20: =IF(B20>=Calculator!$H$7,T19*(1+Calculator!$H$3)-E20,FV(Calculator!$H$1,B20+Calculator!$H$8-Calculator!$B$2, -Calculator!$C$17,-Calculator!$C$13)) -> 5039234.8 | U20: =IF(B20>=Calculator!$H$7,U19*(1+Calculator!$H$3)-F20,FV(Calculator!$H$1,B20+Calculator!$H$8-Calculator!$B$2, -Calculator!$D$17,-Calculator!$D$13)) -> 481293.62 | V20: =IF(B20>=Calculator!$H$7,V19*(1+Calculator!$H$3)-G20,FV(Calculator!$H$1,B20+Calculator!$H$8-Calculator!$B$2, -Calculator!$E$17,-Calculator!$E$13)) -> 2020713 | W20: =IF(B20>=Calculator!$H$7,W19*(1+Calculator!$H$3)-H20,FV(Calculator!$H$1,B20+Calculator!$H$8-Calculator!$B$2, -Calculator!$F$17,-Calculator!$F$13))+P20 -> -884249.48 | X20: =D20+E20+G20+H20 -> 313944.95 | Y20: =Y19*(1+Calculator!$H$6) -> 48697.512 | Z20: =IF(X20>0,D20*0.15+F20+Y20,0) -> 73781.691 | AA20: =X20-Z20 -> 240163.26 | AB20: =AA20*Calculator!$H$5 -> 48032.652 | AC20: =IF((X20+Z20)=0,0,AB20/(X20+Z20)*100) -> 12.388277 | AD20: =T20-T19 -> 239963.56
A21: 2039 | B21: =A21-Calculator!$H$8 -> 66 | D21: =IF(D20=0,IF(B21>=Calculator!$H$10,Calculator!$H$11,0)*Calculator!$H$17,D20*(1+Calculator!$H$6)) -> 46794.342 | E21: =IF(B21>=Calculator!$H$9,T20*Calculator!$H$14,0) -> 201569.39 | F21: =IF(B21>=Calculator!$H$9,U20*Calculator!$H$14,0) -> 19251.745 | G21: =IF(B21>=Calculator!$H$7,V20*Calculator!$H$14,0) -> 80828.52 | H21: =IF(B21>=Calculator!$H$7,IF(W20<=0,0,W20*Calculator!$H$14),0) -> 0 | I21: =IF(I20=0,IF(B21>=Calculator!$H$7,Calculator!$H$12,0),I20*(1+Calculator!$H$6)) -> 0 | J21: =(D21*0.85+E21+H21+I21)*(1-Calculator!$H$5)+D21*0.15+(G21)*(1-Calculator!$H$4)+F21 -> 292092.23 | K21: =D21+E21+F21+G21+H21+I21 -> 348444 | L21: =K21-AB21 -> 297988.81 | M21: =IF(B21=Calculator!$C$2,Calculator!$B$8,M20*(1+Calculator!$H$6)) -> 219789.7 | O21: =M21+N21 -> 219789.7 | P21: =L21-O21 -> 78199.108 | Q21: =IF(Calculator!$H$18="Y",Q20+IF(Q20<0,Q20*Calculator!$H$2,Q20*Calculator!$H$3)+P21,0) -> 0 | R21: =T21+U21+V21+W21 -> 7032670.7 | S21: =Q21+R21 -> 7032670.7 | T21: =IF(B21>=Calculator!$H$7,T20*(1+Calculator!$H$3)-E21,FV(Calculator!$H$1,B21+Calculator!$H$8-Calculator!$B$2, -Calculator!$C$17,-Calculator!$C$13)) -> 5291196.5 | U21: =IF(B21>=Calculator!$H$7,U20*(1+Calculator!$H$3)-F21,FV(Calculator!$H$1,B21+Calculator!$H$8-Calculator!$B$2, -Calculator!$D$17,-Calculator!$D$13)) -> 505358.3 | V21: =IF(B21>=Calculator!$H$7,V20*(1+Calculator!$H$3)-G21,FV(Calculator!$H$1,B21+Calculator!$H$8-Calculator!$B$2, -Calculator!$E$17,-Calculator!$E$13)) -> 2121748.7 | W21: =IF(B21>=Calculator!$H$7,W20*(1+Calculator!$H$3)-H21,FV(Calculator!$H$1,B21+Calculator!$H$8-Calculator!$B$2, -Calculator!$F$17,-Calculator!$F$13))+P21 -> -885632.82 | X21: =D21+E21+G21+H21 -> 329192.26 | Y21: =Y20*(1+Calculator!$H$6) -> 50645.413 | Z21: =IF(X21>0,D21*0.15+F21+Y21,0) -> 76916.309 | AA21: =X21-Z21 -> 252275.95 | AB21: =AA21*Calculator!$H$5 -> 50455.189 | AC21: =IF((X21+Z21)=0,0,AB21/(X21+Z21)*100) -> 12.424064 | AD21: =T21-T20 -> 251961.74
A22: 2040 | B22: =A22-Calculator!$H$8 -> 67 | D22: =IF(D21=0,IF(B22>=Calculator!$H$10,Calculator!$H$11,0)*Calculator!$H$17,D21*(1+Calculator!$H$6)) -> 48666.116 | E22: =IF(B22>=Calculator!$H$9,T21*Calculator!$H$14,0) -> 211647.86 | F22: =IF(B22>=Calculator!$H$9,U21*Calculator!$H$14,0) -> 20214.332 | G22: =IF(B22>=Calculator!$H$7,V21*Calculator!$H$14,0) -> 84869.947 | H22: =IF(B22>=Calculator!$H$7,IF(W21<=0,0,W21*Calculator!$H$14),0) -> 0 | I22: =IF(I21=0,IF(B22>=Calculator!$H$7,Calculator!$H$12,0),I21*(1+Calculator!$H$6)) -> 0 | J22: =(D22*0.85+E22+H22+I22)*(1-Calculator!$H$5)+D22*0.15+(G22)*(1-Calculator!$H$4)+F22 -> 306308.45 | K22: =D22+E22+F22+G22+H22+I22 -> 365398.26 | L22: =K22-AB22 -> 312398.57 | M22: =IF(B22=Calculator!$C$2,Calculator!$B$8,M21*(1+Calculator!$H$6)) -> 228581.29 | O22: =M22+N22 -> 228581.29 | P22: =L22-O22 -> 83817.276 | Q22: =IF(Calculator!$H$18="Y",Q21+IF(Q21<0,Q21*Calculator!$H$2,Q21*Calculator!$H$3)+P22,0) -> 0 | R22: =T22+U22+V22+W22 -> 7432696.2 | S22: =Q22+R22 -> 7432696.2 | T22: =IF(B22>=Calculator!$H$7,T21*(1+Calculator!$H$3)-E22,FV(Calculator!$H$1,B22+Calculator!$H$8-Calculator!$B$2, -Calculator!$C$17,-Calculator!$C$13)) -> 5555756.4 | U22: =IF(B22>=Calculator!$H$7,U21*(1+Calculator!$H$3)-F22,FV(Calculator!$H$1,B22+Calculator!$H$8-Calculator!$B$2, -Calculator!$D$17,-Calculator!$D$13)) -> 530626.22 | V22: =IF(B22>=Calculator!$H$7,V21*(1+Calculator!$H$3)-G22,FV(Calculator!$H$1,B22+Calculator!$H$8-Calculator!$B$2, -Calculator!$E$17,-Calculator!$E$13)) -> 2227836.1 | W22: =IF(B22>=Calculator!$H$7,W21*(1+Calculator!$H$3)-H22,FV(Calculator!$H$1,B22+Calculator!$H$8-Calculator!$B$2, -Calculator!$F$17,-Calculator!$F$13))+P22 -> -881522.5 | X22: =D22+E22+G22+H22 -> 345183.92 | Y22: =Y21*(1+Calculator!$H$6) -> 52671.229 | Z22: =IF(X22>0,D22*0.15+F22+Y22,0) -> 80185.479 | AA22: =X22-Z22 -> 264998.45 | AB22: =AA22*Calculator!$H$5 -> 52999.689 | AC22: =IF((X22+Z22)=0,0,AB22/(X22+Z22)*100) -> 12.459685 | AD22: =T22-T21 -> 264559.83
A23: 2041 | B23: =A23-Calculator!$H$8 -> 68 | D23: =IF(D22=0,IF(B23>=Calculator!$H$10,Calculator!$H$11,0)*Calculator!$H$17,D22*(1+Calculator!$H$6)) -> 50612.761 | E23: =IF(B23>=Calculator!$H$9,T22*Calculator!$H$14,0) -> 222230.25 | F23: =IF(B23>=Calculator!$H$9,U22*Calculator!$H$14,0) -> 21225.049 | G23: =IF(B23>=Calculator!$H$7,V22*Calculator!$H$14,0) -> 89113.444 | H23: =IF(B23>=Calculator!$H$7,IF(W22<=0,0,W22*Calculator!$H$14),0) -> 0 | I23: =IF(I22=0,IF(B23>=Calculator!$H$7,Calculator!$H$12,0),I22*(1+Calculator!$H$6)) -> 0 | J23: =(D23*0.85+E23+H23+I23)*(1-Calculator!$H$5)+D23*0.15+(G23)*(1-Calculator!$H$4)+F23 -> 321219.94 | K23: =D23+E23+F23+G23+H23+I23 -> 383181.51 | L23: =K23-AB23 -> 327509.22 | M23: =IF(B23=Calculator!$C$2,Calculator!$B$8,M22*(1+Calculator!$H$6)) -> 237724.54 | O23: =M23+N23 -> 237724.54 | P23: =L23-O23 -> 89784.682 | Q23: =IF(Calculator!$H$18="Y",Q22+IF(Q22<0,Q22*Calculator!$H$2,Q22*Calculator!$H$3)+P23,0) -> 0 | R23: =T23+U23+V23+W23 -> 7858854.8 | S23: =Q23+R23 -> 7858854.8 | T23: =IF(B23>=Calculator!$H$7,T22*(1+Calculator!$H$3)-E23,FV(Calculator!$H$1,B23+Calculator!$H$8-Calculator!$B$2, -Calculator!$C$17,-Calculator!$C$13)) -> 5833544.2 | U23: =IF(B23>=Calculator!$H$7,U22*(1+Calculator!$H$3)-F23,FV(Calculator!$H$1,B23+Calculator!$H$8-Calculator!$B$2, -Calculator!$D$17,-Calculator!$D$13)) -> 557157.53 | V23: =IF(B23>=Calculator!$H$7,V22*(1+Calculator!$H$3)-G23,FV(Calculator!$H$1,B23+Calculator!$H$8-Calculator!$B$2, -Calculator!$E$17,-Calculator!$E$13)) -> 2339227.9 | W23: =IF(B23>=Calculator!$H$7,W22*(1+Calculator!$H$3)-H23,FV(Calculator!$H$1,B23+Calculator!$H$8-Calculator!$B$2, -Calculator!$F$17,-Calculator!$F$13))+P23 -> -871074.84 | X23: =D23+E23+G23+H23 -> 361956.46 | Y23: =Y22*(1+Calculator!$H$6) -> 54778.079 | Z23: =IF(X23>0,D23*0.15+F23+Y23,0) -> 83595.041 | AA23: =X23-Z23 -> 278361.42 | AB23: =AA23*Calculator!$H$5 -> 55672.284 | AC23: =IF((X23+Z23)=0,0,AB23/(X23+Z23)*100) -> 12.49514 | AD23: =T23-T22 -> 277787.82
A24: 2042 | B24: =A24-Calculator!$H$8 -> 69 | D24: =IF(D23=0,IF(B24>=Calculator!$H$10,Calculator!$H$11,0)*Calculator!$H$17,D23*(1+Calculator!$H$6)) -> 52637.271 | E24: =IF(B24>=Calculator!$H$9,T23*Calculator!$H$14,0) -> 233341.77 | F24: =IF(B24>=Calculator!$H$9,U23*Calculator!$H$14,0) -> 22286.301 | G24: =IF(B24>=Calculator!$H$7,V23*Calculator!$H$14,0) -> 93569.116 | H24: =IF(B24>=Calculator!$H$7,IF(W23<=0,0,W23*Calculator!$H$14),0) -> 0 | I24: =IF(I23=0,IF(B24>=Calculator!$H$7,Calculator!$H$12,0),I23*(1+Calculator!$H$6)) -> 0 | J24: =(D24*0.85+E24+H24+I24)*(1-Calculator!$H$5)+D24*0.15+(G24)*(1-Calculator!$H$4)+F24 -> 336860.85 | K24: =D24+E24+F24+G24+H24+I24 -> 401834.46 | L24: =K24-AB24 -> 343355.04 | M24: =IF(B24=Calculator!$C$2,Calculator!$B$8,M23*(1+Calculator!$H$6)) -> 247233.52 | O24: =M24+N24 -> 247233.52 | P24: =L24-O24 -> 96121.519 | Q24: =IF(Calculator!$H$18="Y",Q23+IF(Q23<0,Q23*Calculator!$H$2,Q23*Calculator!$H$3)+P24,0) -> 0 | R24: =T24+U24+V24+W24 -> 8313076 | S24: =Q24+R24 -> 8313076 | T24: =IF(B24>=Calculator!$H$7,T23*(1+Calculator!$H$3)-E24,FV(Calculator!$H$1,B24+Calculator!$H$8-Calculator!$B$2, -Calculator!$C$17,-Calculator!$C$13)) -> 6125221.4 | U24: =IF(B24>=Calculator!$H$7,U23*(1+Calculator!$H$3)-F24,FV(Calculator!$H$1,B24+Calculator!$H$8-Calculator!$B$2, -Calculator!$D$17,-Calculator!$D$13)) -> 585015.4 | V24: =IF(B24>=Calculator!$H$7,V23*(1+Calculator!$H$3)-G24,FV(Calculator!$H$1,B24+Calculator!$H$8-Calculator!$B$2, -Calculator!$E$17,-Calculator!$E$13)) -> 2456189.3 | W24: =IF(B24>=Calculator!$H$7,W23*(1+Calculator!$H$3)-H24,FV(Calculator!$H$1,B24+Calculator!$H$8-Calculator!$B$2, -Calculator!$F$17,-Calculator!$F$13))+P24 -> -853350.06 | X24: =D24+E24+G24+H24 -> 379548.15 | Y24: =Y23*(1+Calculator!$H$6) -> 56969.202 | Z24: =IF(X24>0,D24*0.15+F24+Y24,0) -> 87151.093 | AA24: =X24-Z24 -> 292397.06 | AB24: =AA24*Calculator!$H$5 -> 58479.412 | AC24: =IF((X24+Z24)=0,0,AB24/(X24+Z24)*100) -> 12.530428 | AD24: =T24-T23 -> 291677.21
A25: 2043 | B25: =A25-Calculator!$H$8 -> 70 | D25: =IF(D24=0,IF(B25>=Calculator!$H$10,Calculator!$H$11,0)*Calculator!$H$17,D24*(1+Calculator!$H$6)) -> 54742.762 | E25: =IF(B25>=Calculator!$H$9,T24*Calculator!$H$14,0) -> 245008.86 | F25: =IF(B25>=Calculator!$H$9,U24*Calculator!$H$14,0) -> 23400.616 | G25: =IF(B25>=Calculator!$H$7,V24*Calculator!$H$14,0) -> 98247.572 | H25: =IF(B25>=Calculator!$H$7,IF(W24<=0,0,W24*Calculator!$H$14),0) -> 0 | I25: =IF(I24=0,IF(B25>=Calculator!$H$7,Calculator!$H$12,0),I24*(1+Calculator!$H$6)) -> 0 | J25: =(D25*0.85+E25+H25+I25)*(1-Calculator!$H$5)+D25*0.15+(G25)*(1-Calculator!$H$4)+F25 -> 353267.01 | K25: =D25+E25+F25+G25+H25+I25 -> 421399.81 | L25: =K25-AB25 -> 359971.97 | M25: =IF(B25=Calculator!$C$2,Calculator!$B$8,M24*(1+Calculator!$H$6)) -> 257122.87 | O25: =M25+N25 -> 257122.87 | P25: =L25-O25 -> 102849.1 | Q25: =IF(Calculator!$H$18="Y",Q24+IF(Q24<0,Q24*Calculator!$H$2,Q24*Calculator!$H$3)+P25,0) -> 0 | R25: =T25+U25+V25+W25 -> 8797444.9 | S25: =Q25+R25 -> 8797444.9 | T25: =IF(B25>=Calculator!$H$7,T24*(1+Calculator!$H$3)-E25,FV(Calculator!$H$1,B25+Calculator!$H$8-Calculator!$B$2, -Calculator!$C$17,-Calculator!$C$13)) -> 6431482.5 | U25: =IF(B25>=Calculator!$H$7,U24*(1+Calculator!$H$3)-F25,FV(Calculator!$H$1,B25+Calculator!$H$8-Calculator!$B$2, -Calculator!$D$17,-Calculator!$D$13)) -> 614266.17 | V25: =IF(B25>=Calculator!$H$7,V24*(1+Calculator!$H$3)-G25,FV(Calculator!$H$1,B25+Calculator!$H$8-Calculator!$B$2, -Calculator!$E$17,-Calculator!$E$13)) -> 2578998.8 | W25: =IF(B25>=Calculator!$H$7,W24*(1+Calculator!$H$3)-H25,FV(Calculator!$H$1,B25+Calculator!$H$8-Calculator!$B$2, -Calculator!$F$17,-Calculator!$F$13))+P25 -> -827302.46 | X25: =D25+E25+G25+H25 -> 397999.19 | Y25: =Y24*(1+Calculator!$H$6) -> 59247.97 | Z25: =IF(X25>0,D25*0.15+F25+Y25,0) -> 90860 | AA25: =X25-Z25 -> 307139.19 | AB25: =AA25*Calculator!$H$5 -> 61427.838 | AC25: =IF((X25+Z25)=0,0,AB25/(X25+Z25)*100) -> 12.565548 | AD25: =W25-W24 -> 26047.597
A26: 2044 | B26: =A26-Calculator!$H$8 -> 71 | D26: =IF(D25=0,IF(B26>=Calculator!$H$10,Calculator!$H$11,0)*Calculator!$H$17,D25*(1+Calculator!$H$6)) -> 56932.473 | E26: =IF(B26>=Calculator!$H$9,T25*Calculator!$H$14,0) -> 257259.3 | F26: =IF(B26>=Calculator!$H$9,U25*Calculator!$H$14,0) -> 24570.647 | G26: =IF(B26>=Calculator!$H$7,V25*Calculator!$H$14,0) -> 103159.95 | H26: =IF(B26>=Calculator!$H$7,IF(W25<=0,0,W25*Calculator!$H$14),0) -> 0 | I26: =IF(I25=0,IF(B26>=Calculator!$H$7,Calculator!$H$12,0),I25*(1+Calculator!$H$6)) -> 0 | J26: =(D26*0.85+E26+H26+I26)*(1-Calculator!$H$5)+D26*0.15+(G26)*(1-Calculator!$H$4)+F26 -> 370475.99 | K26: =D26+E26+F26+G26+H26+I26 -> 441922.37 | L26: =K26-AB26 -> 377397.71 | M26: =IF(B26=Calculator!$C$2,Calculator!$B$8,M25*(1+Calculator!$H$6)) -> 267407.78 | O26: =M26+N26 -> 267407.78 | P26: =L26-O26 -> 109989.93 | Q26: =IF(Calculator!$H$18="Y",Q25+IF(Q25<0,Q25*Calculator!$H$2,Q25*Calculator!$H$3)+P26,0) -> 0 | R26: =T26+U26+V26+W26 -> 9314215 | S26: =Q26+R26 -> 9314215 | T26: =IF(B26>=Calculator!$H$7,T25*(1+Calculator!$H$3)-E26,FV(Calculator!$H$1,B26+Calculator!$H$8-Calculator!$B$2, -Calculator!$C$17,-Calculator!$C$13)) -> 6753056.6 | U26: =IF(B26>=Calculator!$H$7,U25*(1+Calculator!$H$3)-F26,FV(Calculator!$H$1,B26+Calculator!$H$8-Calculator!$B$2, -Calculator!$D$17,-Calculator!$D$13)) -> 644979.48 | V26: =IF(B26>=Calculator!$H$7,V25*(1+Calculator!$H$3)-G26,FV(Calculator!$H$1,B26+Calculator!$H$8-Calculator!$B$2, -Calculator!$E$17,-Calculator!$E$13)) -> 2707948.7 | W26: =IF(B26>=Calculator!$H$7,W25*(1+Calculator!$H$3)-H26,FV(Calculator!$H$1,B26+Calculator!$H$8-Calculator!$B$2, -Calculator!$F$17,-Calculator!$F$13))+P26 -> -791769.76 | X26: =D26+E26+G26+H26 -> 417351.72 | Y26: =Y25*(1+Calculator!$H$6) -> 61617.889 | Z26: =IF(X26>0,D26*0.15+F26+Y26,0) -> 94728.406 | AA26: =X26-Z26 -> 322623.32 | AB26: =AA26*Calculator!$H$5 -> 64524.663 | AC26: =IF((X26+Z26)=0,0,AB26/(X26+Z26)*100) -> 12.600501 | AD26: =W26-W25 -> 35532.704
A27: 2045 | B27: =A27-Calculator!$H$8 -> 72 | D27: =IF(D26=0,IF(B27>=Calculator!$H$10,Calculator!$H$11,0)*Calculator!$H$17,D26*(1+Calculator!$H$6)) -> 59209.771 | E27: =IF(B27>=Calculator!$H$9,T26*Calculator!$H$14,0) -> 270122.26 | F27: =IF(B27>=Calculator!$H$9,U26*Calculator!$H$14,0) -> 25799.179 | G27: =IF(B27>=Calculator!$H$7,V26*Calculator!$H$14,0) -> 108317.95 | H27: =IF(B27>=Calculator!$H$7,IF(W26<=0,0,W26*Calculator!$H$14),0) -> 0 | I27: =IF(I26=0,IF(B27>=Calculator!$H$7,Calculator!$H$12,0),I26*(1+Calculator!$H$6)) -> 0 | J27: =(D27*0.85+E27+H27+I27)*(1-Calculator!$H$5)+D27*0.15+(G27)*(1-Calculator!$H$4)+F27 -> 388527.25 | K27: =D27+E27+F27+G27+H27+I27 -> 463449.16 | L27: =K27-AB27 -> 395671.82 | M27: =IF(B27=Calculator!$C$2,Calculator!$B$8,M26*(1+Calculator!$H$6)) -> 278104.09 | O27: =M27+N27 -> 278104.09 | P27: =L27-O27 -> 117567.72 | Q27: =IF(Calculator!$H$18="Y",Q26+IF(Q26<0,Q26*Calculator!$H$2,Q26*Calculator!$H$3)+P27,0) -> 0 | R27: =T27+U27+V27+W27 -> 9865822.7 | S27: =Q27+R27 -> 9865822.7 | T27: =IF(B27>=Calculator!$H$7,T26*(1+Calculator!$H$3)-E27,FV(Calculator!$H$1,B27+Calculator!$H$8-Calculator!$B$2, -Calculator!$C$17,-Calculator!$C$13)) -> 7090709.4 | U27: =IF(B27>=Calculator!$H$7,U26*(1+Calculator!$H$3)-F27,FV(Calculator!$H$1,B27+Calculator!$H$8-Calculator!$B$2, -Calculator!$D$17,-Calculator!$D$13)) -> 677228.46 | V27: =IF(B27>=Calculator!$H$7,V26*(1+Calculator!$H$3)-G27,FV(Calculator!$H$1,B27+Calculator!$H$8-Calculator!$B$2, -Calculator!$E$17,-Calculator!$E$13)) -> 2843346.1 | W27: =IF(B27>=Calculator!$H$7,W26*(1+Calculator!$H$3)-H27,FV(Calculator!$H$1,B27+Calculator!$H$8-Calculator!$B$2, -Calculator!$F$17,-Calculator!$F$13))+P27 -> -745461.31 | X27: =D27+E27+G27+H27 -> 437649.98 | Y27: =Y26*(1+Calculator!$H$6) -> 64082.604 | Z27: =IF(X27>0,D27*0.15+F27+Y27,0) -> 98763.249 | AA27: =X27-Z27 -> 338886.73 | AB27: =AA27*Calculator!$H$5 -> 67777.347 | AC27: =IF((X27+Z27)=0,0,AB27/(X27+Z27)*100) -> 12.635286 | AD27: =W27-W26 -> 46308.446
A28: 2046 | B28: =A28-Calculator!$H$8 -> 73 | C28: =IF(Calculator!$H$15=B28,"Transfer",) | D28: =IF(D27=0,IF(B28>=Calculator!$H$10,Calculator!$H$11,0)*Calculator!$H$17,D27*(1+Calculator!$H$6)) -> 61578.162 | E28: =IF(B28>=Calculator!$H$9,T27*Calculator!$H$14,0) -> 283628.38 | F28: =IF(B28>=Calculator!$H$9,U27*Calculator!$H$14,0) -> 27089.138 | G28: =IF(B28>=Calculator!$H$7,V27*Calculator!$H$14,0) -> 113733.85 | H28: =IF(B28>=Calculator!$H$7,IF(W27<=0,0,W27*Calculator!$H$14),0) -> 0 | I28: =IF(I27=0,IF(B28>=Calculator!$H$7,Calculator!$H$12,0),I27*(1+Calculator!$H$6)) -> 0 | J28: =(D28*0.85+E28+H28+I28)*(1-Calculator!$H$5)+D28*0.15+(G28)*(1-Calculator!$H$4)+F28 -> 407462.18 | K28: =D28+E28+F28+G28+H28+I28 -> 486029.52 | L28: =K28-AB28 -> 414835.8 | M28: =IF(B28=Calculator!$C$2,Calculator!$B$8,M27*(1+Calculator!$H$6)) -> 289228.25 | O28: =M28+N28 -> 289228.25 | P28: =L28-O28 -> 125607.55 | Q28: =IF(Calculator!$H$18="Y",Q27+IF(Q27<0,Q27*Calculator!$H$2,Q27*Calculator!$H$3)+P28,0) -> 0 | R28: =T28+U28+V28+W28 -> 10454903 | S28: =Q28+R28 -> 10454903 | T28: =IF(B28>=Calculator!$H$7,T27*(1+Calculator!$H$3)-E28,FV(Calculator!$H$1,B28+Calculator!$H$8-Calculator!$B$2, -Calculator!$C$17,-Calculator!$C$13)) -> 7445244.9 | U28: =IF(B28>=Calculator!$H$7,U27*(1+Calculator!$H$3)-F28,FV(Calculator!$H$1,B28+Calculator!$H$8-Calculator!$B$2, -Calculator!$D$17,-Calculator!$D$13)) -> 711089.88 | V28: =IF(B28>=Calculator!$H$7,V27*(1+Calculator!$H$3)-G28,FV(Calculator!$H$1,B28+Calculator!$H$8-Calculator!$B$2, -Calculator!$E$17,-Calculator!$E$13)) -> 2985513.4 | W28: =IF(B28>=Calculator!$H$7,W27*(1+Calculator!$H$3)-H28,FV(Calculator!$H$1,B28+Calculator!$H$8-Calculator!$B$2, -Calculator!$F$17,-Calculator!$F$13))+P28 -> -686945.28 | X28: =D28+E28+G28+H28 -> 458940.38 | Y28: =Y27*(1+Calculator!$H$6) -> 66645.908 | Z28: =IF(X28>0,D28*0.15+F28+Y28,0) -> 102971.77 | AA28: =X28-Z28 -> 355968.61 | AB28: =AA28*Calculator!$H$5 -> 71193.723 | AC28: =IF((X28+Z28)=0,0,AB28/(X28+Z28)*100) -> 12.669903 | AD28: =W28-W27 -> 58516.027
A29: 2047 | B29: =A29-Calculator!$H$8 -> 74 | C29: =IF(Calculator!$H$15=B29,"Transfer",) | D29: =IF(D28=0,IF(B29>=Calculator!$H$10,Calculator!$H$11,0)*Calculator!$H$17,D28*(1+Calculator!$H$6)) -> 64041.289 | E29: =IF(B29>=Calculator!$H$9,T28*Calculator!$H$14,0) -> 297809.8 | F29: =IF(B29>=Calculator!$H$9,U28*Calculator!$H$14,0) -> 28443.595 | G29: =IF(B29>=Calculator!$H$7,V28*Calculator!$H$14,0) -> 119420.54 | H29: =IF(B29>=Calculator!$H$7,IF(W28<=0,0,W28*Calculator!$H$14),0) -> 0 | I29: =IF(I28=0,IF(B29>=Calculator!$H$7,Calculator!$H$12,0),I28*(1+Calculator!$H$6)) -> 0 | J29: =(D29*0.85+E29+H29+I29)*(1-Calculator!$H$5)+D29*0.15+(G29)*(1-Calculator!$H$4)+F29 -> 427324.19 | K29: =D29+E29+F29+G29+H29+I29 -> 509715.22 | L29: =K29-AB29 -> 434933.2 | M29: =IF(B29=Calculator!$C$2,Calculator!$B$8,M28*(1+Calculator!$H$6)) -> 300797.39 | O29: =M29+N29 -> 300797.39 | P29: =L29-O29 -> 134135.81 | Q29: =IF(Calculator!$H$18="Y",Q28+IF(Q28<0,Q28*Calculator!$H$2,Q28*Calculator!$H$3)+P29,0) -> 0 | R29: =T29+U29+V29+W29 -> 11084306 | S29: =Q29+R29 -> 11084306 | T29: =IF(B29>=Calculator!$H$7,T28*(1+Calculator!$H$3)-E29,FV(Calculator!$H$1,B29+Calculator!$H$8-Calculator!$B$2, -Calculator!$C$17,-Calculator!$C$13)) -> 7817507.1 | U29: =IF(B29>=Calculator!$H$7,U28*(1+Calculator!$H$3)-F29,FV(Calculator!$H$1,B29+Calculator!$H$8-Calculator!$B$2, -Calculator!$D$17,-Calculator!$D$13)) -> 746644.37 | V29: =IF(B29>=Calculator!$H$7,V28*(1+Calculator!$H$3)-G29,FV(Calculator!$H$1,B29+Calculator!$H$8-Calculator!$B$2, -Calculator!$E$17,-Calculator!$E$13)) -> 3134789.1 | W29: =IF(B29>=Calculator!$H$7,W28*(1+Calculator!$H$3)-H29,FV(Calculator!$H$1,B29+Calculator!$H$8-Calculator!$B$2, -Calculator!$F$17,-Calculator!$F$13))+P29 -> -614634.55 | X29: =D29+E29+G29+H29 -> 481271.62 | Y29: =Y28*(1+Calculator!$H$6) -> 69311.745 | Z29: =IF(X29>0,D29*0.15+F29+Y29,0) -> 107361.53 | AA29: =X29-Z29 -> 373910.09 | AB29: =AA29*Calculator!$H$5 -> 74782.018 | AC29: =IF((X29+Z29)=0,0,AB29/(X29+Z29)*100) -> 12.70435 | AD29: =W29-W28 -> 72310.739
A30: 2048 | B30: =A30-Calculator!$H$8 -> 75 | C30: =IF(Calculator!$H$15=B30,"Transfer",) | D30: =IF(D29=0,IF(B30>=Calculator!$H$10,Calculator!$H$11,0)*Calculator!$H$17,D29*(1+Calculator!$H$6)) -> 66602.94 | E30: =IF(B30>=Calculator!$H$9,T29*Calculator!$H$14,0) -> 312700.29 | F30: =IF(B30>=Calculator!$H$9,U29*Calculator!$H$14,0) -> 29865.775 | G30: =IF(B30>=Calculator!$H$7,V29*Calculator!$H$14,0) -> 125391.56 | H30: =IF(B30>=Calculator!$H$7,IF(W29<=0,0,W29*Calculator!$H$14),0) -> 0 | I30: =IF(I29=0,IF(B30>=Calculator!$H$7,Calculator!$H$12,0),I29*(1+Calculator!$H$6)) -> 0 | J30: =(D30*0.85+E30+H30+I30)*(1-Calculator!$H$5)+D30*0.15+(G30)*(1-Calculator!$H$4)+F30 -> 448158.85 | K30: =D30+E30+F30+G30+H30+I30 -> 534560.57 | L30: =K30-AB30 -> 456009.69 | M30: =IF(B30=Calculator!$C$2,Calculator!$B$8,M29*(1+Calculator!$H$6)) -> 312829.28 | O30: =M30+N30 -> 312829.28 | P30: =L30-O30 -> 143180.41 | Q30: =IF(Calculator!$H$18="Y",Q29+IF(Q29<0,Q29*Calculator!$H$2,Q29*Calculator!$H$3)+P30,0) -> 0 | R30: =T30+U30+V30+W30 -> 11757116 | S30: =Q30+R30 -> 11757116 | T30: =IF(B30>=Calculator!$H$7,T29*(1+Calculator!$H$3)-E30,FV(Calculator!$H$1,B30+Calculator!$H$8-Calculator!$B$2, -Calculator!$C$17,-Calculator!$C$13)) -> 8208382.5 | U30: =IF(B30>=Calculator!$H$7,U29*(1+Calculator!$H$3)-F30,FV(Calculator!$H$1,B30+Calculator!$H$8-Calculator!$B$2, -Calculator!$D$17,-Calculator!$D$13)) -> 783976.59 | V30: =IF(B30>=Calculator!$H$7,V29*(1+Calculator!$H$3)-G30,FV(Calculator!$H$1,B30+Calculator!$H$8-Calculator!$B$2, -Calculator!$E$17,-Calculator!$E$13)) -> 3291528.6 | W30: =IF(B30>=Calculator!$H$7,W29*(1+Calculator!$H$3)-H30,FV(Calculator!$H$1,B30+Calculator!$H$8-Calculator!$B$2, -Calculator!$F$17,-Calculator!$F$13))+P30 -> -526771.24 | X30: =D30+E30+G30+H30 -> 504694.79 | Y30: =Y29*(1+Calculator!$H$6) -> 72084.214 | Z30: =IF(X30>0,D30*0.15+F30+Y30,0) -> 111940.43 | AA30: =X30-Z30 -> 392754.36 | AB30: =AA30*Calculator!$H$5 -> 78550.872 | AC30: =IF((X30+Z30)=0,0,AB30/(X30+Z30)*100) -> 12.738629 | AD30: =W30-W29 -> 87863.304
A31: 2049 | B31: =A31-Calculator!$H$8 -> 76 | C31: =IF(Calculator!$H$15=B31,"Transfer",) | D31: =IF(D30=0,IF(B31>=Calculator!$H$10,Calculator!$H$11,0)*Calculator!$H$17,D30*(1+Calculator!$H$6)) -> 69267.058 | E31: =IF(B31>=Calculator!$H$9,T30*Calculator!$H$14,0) -> 328335.3 | F31: =IF(B31>=Calculator!$H$9,U30*Calculator!$H$14,0) -> 31359.064 | G31: =IF(B31>=Calculator!$H$7,V30*Calculator!$H$14,0) -> 131661.14 | H31: =IF(B31>=Calculator!$H$7,IF(W30<=0,0,W30*Calculator!$H$14),0) -> 0 | I31: =IF(I30=0,IF(B31>=Calculator!$H$7,Calculator!$H$12,0),I30*(1+Calculator!$H$6)) -> 0 | J31: =(D31*0.85+E31+H31+I31)*(1-Calculator!$H$5)+D31*0.15+(G31)*(1-Calculator!$H$4)+F31 -> 470013.99 | K31: =D31+E31+F31+G31+H31+I31 -> 560622.56 | L31: =K31-AB31 -> 478113.21 | M31: =IF(B31=Calculator!$C$2,Calculator!$B$8,M30*(1+Calculator!$H$6)) -> 325342.45 | O31: =M31+N31 -> 325342.45 | P31: =L31-O31 -> 152770.75 | Q31: =IF(Calculator!$H$18="Y",Q30+IF(Q30<0,Q30*Calculator!$H$2,Q30*Calculator!$H$3)+P31,0) -> 0 | R31: =T31+U31+V31+W31 -> 12476672 | S31: =Q31+R31 -> 12476672 | T31: =IF(B31>=Calculator!$H$7,T30*(1+Calculator!$H$3)-E31,FV(Calculator!$H$1,B31+Calculator!$H$8-Calculator!$B$2, -Calculator!$C$17,-Calculator!$C$13)) -> 8618801.6 | U31: =IF(B31>=Calculator!$H$7,U30*(1+Calculator!$H$3)-F31,FV(Calculator!$H$1,B31+Calculator!$H$8-Calculator!$B$2, -Calculator!$D$17,-Calculator!$D$13)) -> 823175.42 | V31: =IF(B31>=Calculator!$H$7,V30*(1+Calculator!$H$3)-G31,FV(Calculator!$H$1,B31+Calculator!$H$8-Calculator!$B$2, -Calculator!$E$17,-Calculator!$E$13)) -> 3456105 | W31: =IF(B31>=Calculator!$H$7,W30*(1+Calculator!$H$3)-H31,FV(Calculator!$H$1,B31+Calculator!$H$8-Calculator!$B$2, -Calculator!$F$17,-Calculator!$F$13))+P31 -> -421409.9 | X31: =D31+E31+G31+H31 -> 529263.5 | Y31: =Y30*(1+Calculator!$H$6) -> 74967.583 | Z31: =IF(X31>0,D31*0.15+F31+Y31,0) -> 116716.71 | AA31: =X31-Z31 -> 412546.8 | AB31: =AA31*Calculator!$H$5 -> 82509.359 | AC31: =IF((X31+Z31)=0,0,AB31/(X31+Z31)*100) -> 12.772738 | AD31: =W31-W30 -> 105361.34
A32: 2050 | B32: =A32-Calculator!$H$8 -> 77 | C32: =IF(Calculator!$H$15=B32,"Transfer",) | D32: =IF(D31=0,IF(B32>=Calculator!$H$10,Calculator!$H$11,0)*Calculator!$H$17,D31*(1+Calculator!$H$6)) -> 72037.74 | E32: =IF(B32>=Calculator!$H$9,T31*Calculator!$H$14,0) -> 344752.06 | F32: =IF(B32>=Calculator!$H$9,U31*Calculator!$H$14,0) -> 32927.017 | G32: =IF(B32>=Calculator!$H$7,V31*Calculator!$H$14,0) -> 138244.2 | H32: =IF(B32>=Calculator!$H$7,IF(W31<=0,0,W31*Calculator!$H$14),0) -> 0 | I32: =IF(I31=0,IF(B32>=Calculator!$H$7,Calculator!$H$12,0),I31*(1+Calculator!$H$6)) -> 0 | J32: =(D32*0.85+E32+H32+I32)*(1-Calculator!$H$5)+D32*0.15+(G32)*(1-Calculator!$H$4)+F32 -> 492939.77 | K32: =D32+E32+F32+G32+H32+I32 -> 587961.02 | L32: =K32-AB32 -> 501294.01 | M32: =IF(B32=Calculator!$C$2,Calculator!$B$8,M31*(1+Calculator!$H$6)) -> 338356.15 | O32: =M32+N32 -> 338356.15 | P32: =L32-O32 -> 162937.86 | Q32: =IF(Calculator!$H$18="Y",Q31+IF(Q31<0,Q31*Calculator!$H$2,Q31*Calculator!$H$3)+P32,0) -> 0 | R32: =T32+U32+V32+W32 -> 13246587 | S32: =Q32+R32 -> 13246587 | T32: =IF(B32>=Calculator!$H$7,T31*(1+Calculator!$H$3)-E32,FV(Calculator!$H$1,B32+Calculator!$H$8-Calculator!$B$2, -Calculator!$C$17,-Calculator!$C$13)) -> 9049741.7 | U32: =IF(B32>=Calculator!$H$7,U31*(1+Calculator!$H$3)-F32,FV(Calculator!$H$1,B32+Calculator!$H$8-Calculator!$B$2, -Calculator!$D$17,-Calculator!$D$13)) -> 864334.19 | V32: =IF(B32>=Calculator!$H$7,V31*(1+Calculator!$H$3)-G32,FV(Calculator!$H$1,B32+Calculator!$H$8-Calculator!$B$2, -Calculator!$E$17,-Calculator!$E$13)) -> 3628910.2 | W32: =IF(B32>=Calculator!$H$7,W31*(1+Calculator!$H$3)-H32,FV(Calculator!$H$1,B32+Calculator!$H$8-Calculator!$B$2, -Calculator!$F$17,-Calculator!$F$13))+P32 -> -296398.93 | X32: =D32+E32+G32+H32 -> 555034 | Y32: =Y31*(1+Calculator!$H$6) -> 77966.286 | Z32: =IF(X32>0,D32*0.15+F32+Y32,0) -> 121698.96 | AA32: =X32-Z32 -> 433335.04 | AB32: =AA32*Calculator!$H$5 -> 86667.008 | AC32: =IF((X32+Z32)=0,0,AB32/(X32+Z32)*100) -> 12.806677 | AD32: =W32-W31 -> 125010.97
A33: 2051 | B33: =A33-Calculator!$H$8 -> 78 | C33: =IF(Calculator!$H$15=B33,"Transfer",) | D33: =IF(D32=0,IF(B33>=Calculator!$H$10,Calculator!$H$11,0)*Calculator!$H$17,D32*(1+Calculator!$H$6)) -> 74919.25 | E33: =IF(B33>=Calculator!$H$9,T32*Calculator!$H$14,0) -> 361989.67 | F33: =IF(B33>=Calculator!$H$9,U32*Calculator!$H$14,0) -> 34573.368 | G33: =IF(B33>=Calculator!$H$7,V32*Calculator!$H$14,0) -> 145156.41 | H33: =IF(B33>=Calculator!$H$7,IF(W32<=0,0,W32*Calculator!$H$14),0) -> 0 | I33: =IF(I32=0,IF(B33>=Calculator!$H$7,Calculator!$H$12,0),I32*(1+Calculator!$H$6)) -> 0 | J33: =(D33*0.85+E33+H33+I33)*(1-Calculator!$H$5)+D33*0.15+(G33)*(1-Calculator!$H$4)+F33 -> 516988.85 | K33: =D33+E33+F33+G33+H33+I33 -> 616638.7 | L33: =K33-AB33 -> 525604.87 | M33: =IF(B33=Calculator!$C$2,Calculator!$B$8,M32*(1+Calculator!$H$6)) -> 351890.4 | O33: =M33+N33 -> 351890.4 | P33: =L33-O33 -> 173714.47 | Q33: =IF(Calculator!$H$18="Y",Q32+IF(Q32<0,Q32*Calculator!$H$2,Q32*Calculator!$H$3)+P33,0) -> 0 | R33: =T33+U33+V33+W33 -> 14070775 | S33: =Q33+R33 -> 14070775 | T33: =IF(B33>=Calculator!$H$7,T32*(1+Calculator!$H$3)-E33,FV(Calculator!$H$1,B33+Calculator!$H$8-Calculator!$B$2, -Calculator!$C$17,-Calculator!$C$13)) -> 9502228.8 | U33: =IF(B33>=Calculator!$H$7,U32*(1+Calculator!$H$3)-F33,FV(Calculator!$H$1,B33+Calculator!$H$8-Calculator!$B$2, -Calculator!$D$17,-Calculator!$D$13)) -> 907550.9 | V33: =IF(B33>=Calculator!$H$7,V32*(1+Calculator!$H$3)-G33,FV(Calculator!$H$1,B33+Calculator!$H$8-Calculator!$B$2, -Calculator!$E$17,-Calculator!$E$13)) -> 3810355.8 | W33: =IF(B33>=Calculator!$H$7,W32*(1+Calculator!$H$3)-H33,FV(Calculator!$H$1,B33+Calculator!$H$8-Calculator!$B$2, -Calculator!$F$17,-Calculator!$F$13))+P33 -> -149360.36 | X33: =D33+E33+G33+H33 -> 582065.33 | Y33: =Y32*(1+Calculator!$H$6) -> 81084.938 | Z33: =IF(X33>0,D33*0.15+F33+Y33,0) -> 126896.19 | AA33: =X33-Z33 -> 455169.13 | AB33: =AA33*Calculator!$H$5 -> 91033.827 | AC33: =IF((X33+Z33)=0,0,AB33/(X33+Z33)*100) -> 12.840447 | AD33: =W33-W32 -> 147038.57
A34: 2052 | B34: =A34-Calculator!$H$8 -> 79 | C34: =IF(Calculator!$H$15=B34,"Transfer",) | D34: =IF(D33=0,IF(B34>=Calculator!$H$10,Calculator!$H$11,0)*Calculator!$H$17,D33*(1+Calculator!$H$6)) -> 77916.02 | E34: =IF(B34>=Calculator!$H$9,T33*Calculator!$H$14,0) -> 380089.15 | F34: =IF(B34>=Calculator!$H$9,U33*Calculator!$H$14,0) -> 36302.036 | G34: =IF(B34>=Calculator!$H$7,V33*Calculator!$H$14,0) -> 152414.23 | H34: =IF(B34>=Calculator!$H$7,IF(W33<=0,0,W33*Calculator!$H$14),0) -> 0 | I34: =IF(I33=0,IF(B34>=Calculator!$H$7,Calculator!$H$12,0),I33*(1+Calculator!$H$6)) -> 0 | J34: =(D34*0.85+E34+H34+I34)*(1-Calculator!$H$5)+D34*0.15+(G34)*(1-Calculator!$H$4)+F34 -> 542216.46 | K34: =D34+E34+F34+G34+H34+I34 -> 646721.44 | L34: =K34-AB34 -> 551101.11 | M34: =IF(B34=Calculator!$C$2,Calculator!$B$8,M33*(1+Calculator!$H$6)) -> 365966.01 | O34: =M34+N34 -> 365966.01 | P34: =L34-O34 -> 185135.1 | Q34: =IF(Calculator!$H$18="Y",Q33+IF(Q33<0,Q33*Calculator!$H$2,Q33*Calculator!$H$3)+P34,0) -> 0 | R34: =T34+U34+V34+W34 -> 14953475 | S34: =Q34+R34 -> 14953475 | T34: =IF(B34>=Calculator!$H$7,T33*(1+Calculator!$H$3)-E34,FV(Calculator!$H$1,B34+Calculator!$H$8-Calculator!$B$2, -Calculator!$C$17,-Calculator!$C$13)) -> 9977340.2 | U34: =IF(B34>=Calculator!$H$7,U33*(1+Calculator!$H$3)-F34,FV(Calculator!$H$1,B34+Calculator!$H$8-Calculator!$B$2, -Calculator!$D$17,-Calculator!$D$13)) -> 952928.45 | V34: =IF(B34>=Calculator!$H$7,V33*(1+Calculator!$H$3)-G34,FV(Calculator!$H$1,B34+Calculator!$H$8-Calculator!$B$2, -Calculator!$E$17,-Calculator!$E$13)) -> 4000873.5 | W34: =IF(B34>=Calculator!$H$7,W33*(1+Calculator!$H$3)-H34,FV(Calculator!$H$1,B34+Calculator!$H$8-Calculator!$B$2, -Calculator!$F$17,-Calculator!$F$13))+P34 -> 22332.31 | X34: =D34+E34+G34+H34 -> 610419.4 | Y34: =Y33*(1+Calculator!$H$6) -> 84328.335 | Z34: =IF(X34>0,D34*0.15+F34+Y34,0) -> 132317.77 | AA34: =X34-Z34 -> 478101.63 | AB34: =AA34*Calculator!$H$5 -> 95620.325 | AC34: =IF((X34+Z34)=0,0,AB34/(X34+Z34)*100) -> 12.874046 | AD34: =W34-W33 -> 171692.67
A35: 2053 | B35: =A35-Calculator!$H$8 -> 80 | C35: =IF(Calculator!$H$15=B35,"Transfer",) -> Transfer | D35: =IF(D34=0,IF(B35>=Calculator!$H$10,Calculator!$H$11,0)*Calculator!$H$17,D34*(1+Calculator!$H$6)) -> 81032.661 | E35: =IF(B35>=Calculator!$H$9,T34*Calculator!$H$14,0) -> 399093.61 | F35: =IF(B35>=Calculator!$H$9,U34*Calculator!$H$14,0) -> 38117.138 | G35: =IF(B35>=Calculator!$H$7,V34*Calculator!$H$14,0) -> 160034.94 | H35: =IF(B35>=Calculator!$H$7,IF(W34<=0,0,W34*Calculator!$H$14),0) -> 893.29239 | I35: =IF(I34=0,IF(B35>=Calculator!$H$7,Calculator!$H$12,0),I34*(1+Calculator!$H$6)) -> 0 | J35: =(D35*0.85+E35+H35+I35)*(1-Calculator!$H$5)+D35*0.15+(G35)*(1-Calculator!$H$4)+F35 -> 569395.21 | K35: =D35+E35+F35+G35+H35+I35 -> 679171.64 | L35: =K35-AB35 -> 578555.44 | M35: =IF(B35=Calculator!$C$2,Calculator!$B$8,M34*(1+Calculator!$H$6)) -> 380604.65 | O35: =M35+N35 -> 380604.65 | P35: =L35-O35 -> 197950.79 | Q35: =IF(Calculator!$H$18="Y",Q34+IF(Q34<0,Q34*Calculator!$H$2,Q34*Calculator!$H$3)+P35,0) -> 0 | R35: =T35+U35+V35+W35 -> 15899099 | S35: =Q35+R35 -> 15899099 | T35: =IF(B35>=Calculator!$H$7,T34*(1+Calculator!$H$3)-E35,FV(Calculator!$H$1,B35+Calculator!$H$8-Calculator!$B$2, -Calculator!$C$17,-Calculator!$C$13)) -> 10476207 | U35: =IF(B35>=Calculator!$H$7,U34*(1+Calculator!$H$3)-F35,FV(Calculator!$H$1,B35+Calculator!$H$8-Calculator!$B$2, -Calculator!$D$17,-Calculator!$D$13)) -> 1000574.9 | V35: =IF(B35>=Calculator!$H$7,V34*(1+Calculator!$H$3)-G35,FV(Calculator!$H$1,B35+Calculator!$H$8-Calculator!$B$2, -Calculator!$E$17,-Calculator!$E$13)) -> 4200917.2 | W35: =IF(B35>=Calculator!$H$7,W34*(1+Calculator!$H$3)-H35,FV(Calculator!$H$1,B35+Calculator!$H$8-Calculator!$B$2, -Calculator!$F$17,-Calculator!$F$13))+P35 -> 221399.72 | X35: =D35+E35+G35+H35 -> 641054.5 | Y35: =Y34*(1+Calculator!$H$6) -> 87701.469 | Z35: =IF(X35>0,D35*0.15+F35+Y35,0) -> 137973.51 | AA35: =X35-Z35 -> 503081 | AB35: =AA35*Calculator!$H$5 -> 100616.2 | AC35: =IF((X35+Z35)=0,0,AB35/(X35+Z35)*100) -> 12.915607 | AD35: =W35-W34 -> 199067.41
A36: 2054 | B36: =A36-Calculator!$H$8 -> 81 | C36: =IF(Calculator!$H$15=B36,"Transfer",) | D36: =IF(D35=0,IF(B36>=Calculator!$H$10,Calculator!$H$11,0)*Calculator!$H$17,D35*(1+Calculator!$H$6)) -> 84273.967 | E36: =IF(B36>=Calculator!$H$9,T35*Calculator!$H$14,0) -> 419048.29 | F36: =IF(B36>=Calculator!$H$9,U35*Calculator!$H$14,0) -> 40022.995 | G36: =IF(B36>=Calculator!$H$7,V35*Calculator!$H$14,0) -> 168036.69 | H36: =IF(B36>=Calculator!$H$7,IF(W35<=0,0,W35*Calculator!$H$14),0) -> 8855.9886 | I36: =IF(I35=0,IF(B36>=Calculator!$H$7,Calculator!$H$12,0),I35*(1+Calculator!$H$6)) -> 0 | J36: =(D36*0.85+E36+H36+I36)*(1-Calculator!$H$5)+D36*0.15+(G36)*(1-Calculator!$H$4)+F36 -> 603526.83 | K36: =D36+E36+F36+G36+H36+I36 -> 720237.93 | L36: =K36-AB36 -> 612969.67 | M36: =IF(B36=Calculator!$C$2,Calculator!$B$8,M35*(1+Calculator!$H$6)) -> 395828.84 | O36: =M36+N36 -> 395828.84 | P36: =L36-O36 -> 217140.83 | Q36: =IF(Calculator!$H$18="Y",Q35+IF(Q35<0,Q35*Calculator!$H$2,Q35*Calculator!$H$3)+P36,0) -> 0 | R36: =T36+U36+V36+W36 -> 16911195 | S36: =Q36+R36 -> 16911195 | T36: =IF(B36>=Calculator!$H$7,T35*(1+Calculator!$H$3)-E36,FV(Calculator!$H$1,B36+Calculator!$H$8-Calculator!$B$2, -Calculator!$C$17,-Calculator!$C$13)) -> 11000018 | U36: =IF(B36>=Calculator!$H$7,U35*(1+Calculator!$H$3)-F36,FV(Calculator!$H$1,B36+Calculator!$H$8-Calculator!$B$2, -Calculator!$D$17,-Calculator!$D$13)) -> 1050603.6 | V36: =IF(B36>=Calculator!$H$7,V35*(1+Calculator!$H$3)-G36,FV(Calculator!$H$1,B36+Calculator!$H$8-Calculator!$B$2, -Calculator!$E$17,-Calculator!$E$13)) -> 4410963.1 | W36: =IF(B36>=Calculator!$H$7,W35*(1+Calculator!$H$3)-H36,FV(Calculator!$H$1,B36+Calculator!$H$8-Calculator!$B$2, -Calculator!$F$17,-Calculator!$F$13))+P36 -> 449610.53 | X36: =D36+E36+G36+H36 -> 680214.93 | Y36: =Y35*(1+Calculator!$H$6) -> 91209.527 | Z36: =IF(X36>0,D36*0.15+F36+Y36,0) -> 143873.62 | AA36: =X36-Z36 -> 536341.32 | AB36: =AA36*Calculator!$H$5 -> 107268.26 | AC36: =IF((X36+Z36)=0,0,AB36/(X36+Z36)*100) -> 13.016594 | AD36: =W36-W35 -> 228210.81
A37: 2055 | B37: =A37-Calculator!$H$8 -> 82 | C37: =IF(Calculator!$H$15=B37,"Transfer",) | D37: =IF(D36=0,IF(B37>=Calculator!$H$10,Calculator!$H$11,0)*Calculator!$H$17,D36*(1+Calculator!$H$6)) -> 87644.926 | E37: =IF(B37>=Calculator!$H$9,T36*Calculator!$H$14,0) -> 440000.7 | F37: =IF(B37>=Calculator!$H$9,U36*Calculator!$H$14,0) -> 42024.144 | G37: =IF(B37>=Calculator!$H$7,V36*Calculator!$H$14,0) -> 176438.52 | H37: =IF(B37>=Calculator!$H$7,IF(W36<=0,0,W36*Calculator!$H$14),0) -> 17984.421 | I37: =IF(I36=0,IF(B37>=Calculator!$H$7,Calculator!$H$12,0),I36*(1+Calculator!$H$6)) -> 0 | J37: =(D37*0.85+E37+H37+I37)*(1-Calculator!$H$5)+D37*0.15+(G37)*(1-Calculator!$H$4)+F37 -> 639952.2 | K37: =D37+E37+F37+G37+H37+I37 -> 764092.72 | L37: =K37-AB37 -> 649684.76 | M37: =IF(B37=Calculator!$C$2,Calculator!$B$8,M36*(1+Calculator!$H$6)) -> 411661.99 | O37: =M37+N37 -> 411661.99 | P37: =L37-O37 -> 238022.77 | Q37: =IF(Calculator!$H$18="Y",Q36+IF(Q36<0,Q36*Calculator!$H$2,Q36*Calculator!$H$3)+P37,0) -> 0 | R37: =T37+U37+V37+W37 -> 17994777 | S37: =Q37+R37 -> 17994777 | T37: =IF(B37>=Calculator!$H$7,T36*(1+Calculator!$H$3)-E37,FV(Calculator!$H$1,B37+Calculator!$H$8-Calculator!$B$2, -Calculator!$C$17,-Calculator!$C$13)) -> 11550018 | U37: =IF(B37>=Calculator!$H$7,U36*(1+Calculator!$H$3)-F37,FV(Calculator!$H$1,B37+Calculator!$H$8-Calculator!$B$2, -Calculator!$D$17,-Calculator!$D$13)) -> 1103133.8 | V37: =IF(B37>=Calculator!$H$7,V36*(1+Calculator!$H$3)-G37,FV(Calculator!$H$1,B37+Calculator!$H$8-Calculator!$B$2, -Calculator!$E$17,-Calculator!$E$13)) -> 4631511.2 | W37: =IF(B37>=Calculator!$H$7,W36*(1+Calculator!$H$3)-H37,FV(Calculator!$H$1,B37+Calculator!$H$8-Calculator!$B$2, -Calculator!$F$17,-Calculator!$F$13))+P37 -> 710113.83 | X37: =D37+E37+G37+H37 -> 722068.57 | Y37: =Y36*(1+Calculator!$H$6) -> 94857.909 | Z37: =IF(X37>0,D37*0.15+F37+Y37,0) -> 150028.79 | AA37: =X37-Z37 -> 572039.78 | AB37: =AA37*Calculator!$H$5 -> 114407.96 | AC37: =IF((X37+Z37)=0,0,AB37/(X37+Z37)*100) -> 13.118714 | AD37: =W37-W36 -> 260503.3
A38: 2056 | B38: =A38-Calculator!$H$8 -> 83 | C38: =IF(Calculator!$H$15=B38,"Transfer",) | D38: =IF(D37=0,IF(B38>=Calculator!$H$10,Calculator!$H$11,0)*Calculator!$H$17,D37*(1+Calculator!$H$6)) -> 91150.723 | E38: =IF(B38>=Calculator!$H$9,T37*Calculator!$H$14,0) -> 462000.74 | F38: =IF(B38>=Calculator!$H$9,U37*Calculator!$H$14,0) -> 44125.352 | G38: =IF(B38>=Calculator!$H$7,V37*Calculator!$H$14,0) -> 185260.45 | H38: =IF(B38>=Calculator!$H$7,IF(W37<=0,0,W37*Calculator!$H$14),0) -> 28404.553 | I38: =IF(I37=0,IF(B38>=Calculator!$H$7,Calculator!$H$12,0),I37*(1+Calculator!$H$6)) -> 0 | J38: =(D38*0.85+E38+H38+I38)*(1-Calculator!$H$5)+D38*0.15+(G38)*(1-Calculator!$H$4)+F38 -> 678839.09 | K38: =D38+E38+F38+G38+H38+I38 -> 810941.82 | L38: =K38-AB38 -> 688868.56 | M38: =IF(B38=Calculator!$C$2,Calculator!$B$8,M37*(1+Calculator!$H$6)) -> 428128.47 | O38: =M38+N38 -> 428128.47 | P38: =L38-O38 -> 260740.09 | Q38: =IF(Calculator!$H$18="Y",Q37+IF(Q37<0,Q37*Calculator!$H$2,Q37*Calculator!$H$3)+P38,0) -> 0 | R38: =T38+U38+V38+W38 -> 19155256 | S38: =Q38+R38 -> 19155256 | T38: =IF(B38>=Calculator!$H$7,T37*(1+Calculator!$H$3)-E38,FV(Calculator!$H$1,B38+Calculator!$H$8-Calculator!$B$2, -Calculator!$C$17,-Calculator!$C$13)) -> 12127519 | U38: =IF(B38>=Calculator!$H$7,U37*(1+Calculator!$H$3)-F38,FV(Calculator!$H$1,B38+Calculator!$H$8-Calculator!$B$2, -Calculator!$D$17,-Calculator!$D$13)) -> 1158290.5 | V38: =IF(B38>=Calculator!$H$7,V37*(1+Calculator!$H$3)-G38,FV(Calculator!$H$1,B38+Calculator!$H$8-Calculator!$B$2, -Calculator!$E$17,-Calculator!$E$13)) -> 4863086.8 | W38: =IF(B38>=Calculator!$H$7,W37*(1+Calculator!$H$3)-H38,FV(Calculator!$H$1,B38+Calculator!$H$8-Calculator!$B$2, -Calculator!$F$17,-Calculator!$F$13))+P38 -> 1006359.6 | X38: =D38+E38+G38+H38 -> 766816.46 | Y38: =Y37*(1+Calculator!$H$6) -> 98652.225 | Z38: =IF(X38>0,D38*0.15+F38+Y38,0) -> 156450.18 | AA38: =X38-Z38 -> 610366.28 | AB38: =AA38*Calculator!$H$5 -> 122073.26 | AC38: =IF((X38+Z38)=0,0,AB38/(X38+Z38)*100) -> 13.221885 | AD38: =W38-W37 -> 296245.78
A39: 2057 | B39: =A39-Calculator!$H$8 -> 84 | C39: =IF(Calculator!$H$15=B39,"Transfer",) | D39: =IF(D38=0,IF(B39>=Calculator!$H$10,Calculator!$H$11,0)*Calculator!$H$17,D38*(1+Calculator!$H$6)) -> 94796.752 | E39: =IF(B39>=Calculator!$H$9,T38*Calculator!$H$14,0) -> 485100.78 | F39: =IF(B39>=Calculator!$H$9,U38*Calculator!$H$14,0) -> 46331.619 | G39: =IF(B39>=Calculator!$H$7,V38*Calculator!$H$14,0) -> 194523.47 | H39: =IF(B39>=Calculator!$H$7,IF(W38<=0,0,W38*Calculator!$H$14),0) -> 40254.384 | I39: =IF(I38=0,IF(B39>=Calculator!$H$7,Calculator!$H$12,0),I38*(1+Calculator!$H$6)) -> 0 | J39: =(D39*0.85+E39+H39+I39)*(1-Calculator!$H$5)+D39*0.15+(G39)*(1-Calculator!$H$4)+F39 -> 720368.18 | K39: =D39+E39+F39+G39+H39+I39 -> 861007 | L39: =K39-AB39 -> 730701.82 | M39: =IF(B39=Calculator!$C$2,Calculator!$B$8,M38*(1+Calculator!$H$6)) -> 445253.61 | O39: =M39+N39 -> 445253.61 | P39: =L39-O39 -> 285448.21 | Q39: =IF(Calculator!$H$18="Y",Q38+IF(Q38<0,Q38*Calculator!$H$2,Q38*Calculator!$H$3)+P39,0) -> 0 | R39: =T39+U39+V39+W39 -> 20398467 | S39: =Q39+R39 -> 20398467 | T39: =IF(B39>=Calculator!$H$7,T38*(1+Calculator!$H$3)-E39,FV(Calculator!$H$1,B39+Calculator!$H$8-Calculator!$B$2, -Calculator!$C$17,-Calculator!$C$13)) -> 12733895 | U39: =IF(B39>=Calculator!$H$7,U38*(1+Calculator!$H$3)-F39,FV(Calculator!$H$1,B39+Calculator!$H$8-Calculator!$B$2, -Calculator!$D$17,-Calculator!$D$13)) -> 1216205 | V39: =IF(B39>=Calculator!$H$7,V38*(1+Calculator!$H$3)-G39,FV(Calculator!$H$1,B39+Calculator!$H$8-Calculator!$B$2, -Calculator!$E$17,-Calculator!$E$13)) -> 5106241.1 | W39: =IF(B39>=Calculator!$H$7,W38*(1+Calculator!$H$3)-H39,FV(Calculator!$H$1,B39+Calculator!$H$8-Calculator!$B$2, -Calculator!$F$17,-Calculator!$F$13))+P39 -> 1342125.8 | X39: =D39+E39+G39+H39 -> 814675.38 | Y39: =Y38*(1+Calculator!$H$6) -> 102598.31 | Z39: =IF(X39>0,D39*0.15+F39+Y39,0) -> 163149.45 | AA39: =X39-Z39 -> 651525.94 | AB39: =AA39*Calculator!$H$5 -> 130305.19 | AC39: =IF((X39+Z39)=0,0,AB39/(X39+Z39)*100) -> 13.326026 | AD39: =W39-W38 -> 335766.19
... A48: 2066 | B48: =A48-Calculator!$H$8 -> 93 | C48: =IF(Calculator!$H$15=B48,"Transfer",) | D48: =IF(D47=0,IF(B48>=Calculator!$H$10,Calculator!$H$11,0)*Calculator!$H$17,D47*(1+Calculator!$H$6)) -> 134925.34 | E48: =IF(B48>=Calculator!$H$9,T47*Calculator!$H$14,0) -> 752550.52 | F48: =IF(B48>=Calculator!$H$9,U47*Calculator!$H$14,0) -> 71875.548 | G48: =IF(B48>=Calculator!$H$7,V47*Calculator!$H$14,0) -> 301769.75 | H48: =IF(B48>=Calculator!$H$7,IF(W47<=0,0,W47*Calculator!$H$14),0) -> 241532.53 | I48: =IF(I47=0,IF(B48>=Calculator!$H$7,Calculator!$H$12,0),I47*(1+Calculator!$H$6)) -> 0 | J48: =(D48*0.85+E48+H48+I48)*(1-Calculator!$H$5)+D48*0.15+(G48)*(1-Calculator!$H$4)+F48 -> 1250722.8 | K48: =D48+E48+F48+G48+H48+I48 -> 1502653.7 | L48: =K48-AB48 -> 1264126.8 | M48: =IF(B48=Calculator!$C$2,Calculator!$B$8,M47*(1+Calculator!$H$6)) -> 633734.72 | O48: =M48+N48 -> 633734.72 | P48: =L48-O48 -> 630392.08 | Q48: =IF(Calculator!$H$18="Y",Q47+IF(Q47<0,Q47*Calculator!$H$2,Q47*Calculator!$H$3)+P48,0) -> 0 | R48: =T48+U48+V48+W48 -> 36533261 | S48: =Q48+R48 -> 36533261 | T48: =IF(B48>=Calculator!$H$7,T47*(1+Calculator!$H$3)-E48,FV(Calculator!$H$1,B48+Calculator!$H$8-Calculator!$B$2, -Calculator!$C$17,-Calculator!$C$13)) -> 19754451 | U48: =IF(B48>=Calculator!$H$7,U47*(1+Calculator!$H$3)-F48,FV(Calculator!$H$1,B48+Calculator!$H$8-Calculator!$B$2, -Calculator!$D$17,-Calculator!$D$13)) -> 1886733.1 | V48: =IF(B48>=Calculator!$H$7,V47*(1+Calculator!$H$3)-G48,FV(Calculator!$H$1,B48+Calculator!$H$8-Calculator!$B$2, -Calculator!$E$17,-Calculator!$E$13)) -> 7921456 | W48: =IF(B48>=Calculator!$H$7,W47*(1+Calculator!$H$3)-H48,FV(Calculator!$H$1,B48+Calculator!$H$8-Calculator!$B$2, -Calculator!$F$17,-Calculator!$F$13))+P48 -> 6970620.9 | X48: =D48+E48+G48+H48 -> 1430778.1 | Y48: =Y47*(1+Calculator!$H$6) -> 146029.39 | Z48: =IF(X48>0,D48*0.15+F48+Y48,0) -> 238143.74 | AA48: =X48-Z48 -> 1192634.4 | AB48: =AA48*Calculator!$H$5 -> 238526.88 | AC48: =IF((X48+Z48)=0,0,AB48/(X48+Z48)*100) -> 14.292274 | AD48: =W48-W47 -> 932307.74
A49: 2067 | B49: =A49-Calculator!$H$8 -> 94 | D49: =IF(D48=0,IF(B49>=Calculator!$H$10,Calculator!$H$11,0)*Calculator!$H$17,D48*(1+Calculator!$H$6)) -> 140322.35 | E49: =IF(B49>=Calculator!$H$9,T48*Calculator!$H$14,0) -> 790178.05 | F49: =IF(B49>=Calculator!$H$9,U48*Calculator!$H$14,0) -> 75469.326 | G49: =IF(B49>=Calculator!$H$7,V48*Calculator!$H$14,0) -> 316858.24 | H49: =IF(B49>=Calculator!$H$7,IF(W48<=0,0,W48*Calculator!$H$14),0) -> 278824.84 | I49: =IF(I48=0,IF(B49>=Calculator!$H$7,Calculator!$H$12,0),I48*(1+Calculator!$H$6)) -> 0 | J49: =(D49*0.85+E49+H49+I49)*(1-Calculator!$H$5)+D49*0.15+(G49)*(1-Calculator!$H$4)+F49 -> 1332311.6 | K49: =D49+E49+F49+G49+H49+I49 -> 1601652.8 | L49: =K49-AB49 -> 1346093.8 | M49: =IF(B49=Calculator!$C$2,Calculator!$B$8,M48*(1+Calculator!$H$6)) -> 659084.11 | O49: =M49+N49 -> 659084.11 | P49: =L49-O49 -> 687009.64 | Q49: =IF(Calculator!$H$18="Y",Q48+IF(Q48<0,Q48*Calculator!$H$2,Q48*Calculator!$H$3)+P49,0) -> 0 | R49: =T49+U49+V49+W49 -> 39046934 | S49: =Q49+R49 -> 39046934 | T49: =IF(B49>=Calculator!$H$7,T48*(1+Calculator!$H$3)-E49,FV(Calculator!$H$1,B49+Calculator!$H$8-Calculator!$B$2, -Calculator!$C$17,-Calculator!$C$13)) -> 20742174 | U49: =IF(B49>=Calculator!$H$7,U48*(1+Calculator!$H$3)-F49,FV(Calculator!$H$1,B49+Calculator!$H$8-Calculator!$B$2, -Calculator!$D$17,-Calculator!$D$13)) -> 1981069.8 | V49: =IF(B49>=Calculator!$H$7,V48*(1+Calculator!$H$3)-G49,FV(Calculator!$H$1,B49+Calculator!$H$8-Calculator!$B$2, -Calculator!$E$17,-Calculator!$E$13)) -> 8317528.8 | W49: =IF(B49>=Calculator!$H$7,W48*(1+Calculator!$H$3)-H49,FV(Calculator!$H$1,B49+Calculator!$H$8-Calculator!$B$2, -Calculator!$F$17,-Calculator!$F$13))+P49 -> 8006161.6 | X49: =D49+E49+G49+H49 -> 1526183.5 | Y49: =Y48*(1+Calculator!$H$6) -> 151870.57 | Z49: =IF(X49>0,D49*0.15+F49+Y49,0) -> 248388.25 | AA49: =X49-Z49 -> 1277795.2 | AB49: =AA49*Calculator!$H$5 -> 255559.05 | AC49: =IF((X49+Z49)=0,0,AB49/(X49+Z49)*100) -> 14.401167 | AD49: =W49-W48 -> 1035540.7
A50: 2068 | B50: =A50-Calculator!$H$8 -> 95 | D50: =IF(D49=0,IF(B50>=Calculator!$H$10,Calculator!$H$11,0)*Calculator!$H$17,D49*(1+Calculator!$H$6)) -> 145935.24 | E50: =IF(B50>=Calculator!$H$9,T49*Calculator!$H$14,0) -> 829686.95 | F50: =IF(B50>=Calculator!$H$9,U49*Calculator!$H$14,0) -> 79242.792 | G50: =IF(B50>=Calculator!$H$7,V49*Calculator!$H$14,0) -> 332701.15 | H50: =IF(B50>=Calculator!$H$7,IF(W49<=0,0,W49*Calculator!$H$14),0) -> 320246.46 | I50: =IF(I49=0,IF(B50>=Calculator!$H$7,Calculator!$H$12,0),I49*(1+Calculator!$H$6)) -> 0 | J50: =(D50*0.85+E50+H50+I50)*(1-Calculator!$H$5)+D50*0.15+(G50)*(1-Calculator!$H$4)+F50 -> 1419746.8 | K50: =D50+E50+F50+G50+H50+I50 -> 1707812.6 | L50: =K50-AB50 -> 1433914.3 | M50: =IF(B50=Calculator!$C$2,Calculator!$B$8,M49*(1+Calculator!$H$6)) -> 685447.48 | O50: =M50+N50 -> 685447.48 | P50: =L50-O50 -> 748466.86 | Q50: =IF(Calculator!$H$18="Y",Q49+IF(Q49<0,Q49*Calculator!$H$2,Q49*Calculator!$H$3)+P50,0) -> 0 | R50: =T50+U50+V50+W50 -> 41747747 | S50: =Q50+R50 -> 41747747 | T50: =IF(B50>=Calculator!$H$7,T49*(1+Calculator!$H$3)-E50,FV(Calculator!$H$1,B50+Calculator!$H$8-Calculator!$B$2, -Calculator!$C$17,-Calculator!$C$13)) -> 21779282 | U50: =IF(B50>=Calculator!$H$7,U49*(1+Calculator!$H$3)-F50,FV(Calculator!$H$1,B50+Calculator!$H$8-Calculator!$B$2, -Calculator!$D$17,-Calculator!$D$13)) -> 2080123.3 | V50: =IF(B50>=Calculator!$H$7,V49*(1+Calculator!$H$3)-G50,FV(Calculator!$H$1,B50+Calculator!$H$8-Calculator!$B$2, -Calculator!$E$17,-Calculator!$E$13)) -> 8733405.2 | W50: =IF(B50>=Calculator!$H$7,W49*(1+Calculator!$H$3)-H50,FV(Calculator!$H$1,B50+Calculator!$H$8-Calculator!$B$2, -Calculator!$F$17,-Calculator!$F$13))+P50 -> 9154936.5 | X50: =D50+E50+G50+H50 -> 1628569.8 | Y50: =Y49*(1+Calculator!$H$6) -> 157945.39 | Z50: =IF(X50>0,D50*0.15+F50+Y50,0) -> 259078.47 | AA50: =X50-Z50 -> 1369491.3 | AB50: =AA50*Calculator!$H$5 -> 273898.27 | AC50: =IF((X50+Z50)=0,0,AB50/(X50+Z50)*100) -> 14.510027 | AD50: =W50-W49 -> 1148774.9
A51: 2069 | B51: =A51-Calculator!$H$8 -> 96 | D51: =IF(D50=0,IF(B51>=Calculator!$H$10,Calculator!$H$11,0)*Calculator!$H$17,D50*(1+Calculator!$H$6)) -> 151772.65 | E51: =IF(B51>=Calculator!$H$9,T50*Calculator!$H$14,0) -> 871171.3 | F51: =IF(B51>=Calculator!$H$9,U50*Calculator!$H$14,0) -> 83204.932 | G51: =IF(B51>=Calculator!$H$7,V50*Calculator!$H$14,0) -> 349336.21 | H51: =IF(B51>=Calculator!$H$7,IF(W50<=0,0,W50*Calculator!$H$14),0) -> 366197.46 | I51: =IF(I50=0,IF(B51>=Calculator!$H$7,Calculator!$H$12,0),I50*(1+Calculator!$H$6)) -> 0 | J51: =(D51*0.85+E51+H51+I51)*(1-Calculator!$H$5)+D51*0.15+(G51)*(1-Calculator!$H$4)+F51 -> 1513473.8 | K51: =D51+E51+F51+G51+H51+I51 -> 1821682.6 | L51: =K51-AB51 -> 1528033.8 | M51: =IF(B51=Calculator!$C$2,Calculator!$B$8,M50*(1+Calculator!$H$6)) -> 712865.38 | O51: =M51+N51 -> 712865.38 | P51: =L51-O51 -> 815168.46 | Q51: =IF(Calculator!$H$18="Y",Q50+IF(Q50<0,Q50*Calculator!$H$2,Q50*Calculator!$H$3)+P51,0) -> 0 | R51: =T51+U51+V51+W51 -> 44650303 | S51: =Q51+R51 -> 44650303 | T51: =IF(B51>=Calculator!$H$7,T50*(1+Calculator!$H$3)-E51,FV(Calculator!$H$1,B51+Calculator!$H$8-Calculator!$B$2, -Calculator!$C$17,-Calculator!$C$13)) -> 22868247 | U51: =IF(B51>=Calculator!$H$7,U50*(1+Calculator!$H$3)-F51,FV(Calculator!$H$1,B51+Calculator!$H$8-Calculator!$B$2, -Calculator!$D$17,-Calculator!$D$13)) -> 2184129.5 | V51: =IF(B51>=Calculator!$H$7,V50*(1+Calculator!$H$3)-G51,FV(Calculator!$H$1,B51+Calculator!$H$8-Calculator!$B$2, -Calculator!$E$17,-Calculator!$E$13)) -> 9170075.5 | W51: =IF(B51>=Calculator!$H$7,W50*(1+Calculator!$H$3)-H51,FV(Calculator!$H$1,B51+Calculator!$H$8-Calculator!$B$2, -Calculator!$F$17,-Calculator!$F$13))+P51 -> 10427852 | X51: =D51+E51+G51+H51 -> 1738477.6 | Y51: =Y50*(1+Calculator!$H$6) -> 164263.21 | Z51: =IF(X51>0,D51*0.15+F51+Y51,0) -> 270234.04 | AA51: =X51-Z51 -> 1468243.6 | AB51: =AA51*Calculator!$H$5 -> 293648.72 | AC51: =IF((X51+Z51)=0,0,AB51/(X51+Z51)*100) -> 14.618759 | AD51: =W51-W50 -> 1272915.3
A52: 2070 | B52: =A52-Calculator!$H$8 -> 97 | D52: =IF(D51=0,IF(B52>=Calculator!$H$10,Calculator!$H$11,0)*Calculator!$H$17,D51*(1+Calculator!$H$6)) -> 157843.56 | E52: =IF(B52>=Calculator!$H$9,T51*Calculator!$H$14,0) -> 914729.86 | F52: =IF(B52>=Calculator!$H$9,U51*Calculator!$H$14,0) -> 87365.178 | G52: =IF(B52>=Calculator!$H$7,V51*Calculator!$H$14,0) -> 366803.02 | H52: =IF(B52>=Calculator!$H$7,IF(W51<=0,0,W51*Calculator!$H$14),0) -> 417114.07 | I52: =IF(I51=0,IF(B52>=Calculator!$H$7,Calculator!$H$12,0),I51*(1+Calculator!$H$6)) -> 0 | J52: =(D52*0.85+E52+H52+I52)*(1-Calculator!$H$5)+D52*0.15+(G52)*(1-Calculator!$H$4)+F52 -> 1613973.2 | K52: =D52+E52+F52+G52+H52+I52 -> 1943855.7 | L52: =K52-AB52 -> 1628932.7 | M52: =IF(B52=Calculator!$C$2,Calculator!$B$8,M51*(1+Calculator!$H$6)) -> 741379.99 | O52: =M52+N52 -> 741379.99 | P52: =L52-O52 -> 887552.69 | Q52: =IF(Calculator!$H$18="Y",Q51+IF(Q51<0,Q51*Calculator!$H$2,Q51*Calculator!$H$3)+P52,0) -> 0 | R52: =T52+U52+V52+W52 -> 47770371 | S52: =Q52+R52 -> 47770371 | T52: =IF(B52>=Calculator!$H$7,T51*(1+Calculator!$H$3)-E52,FV(Calculator!$H$1,B52+Calculator!$H$8-Calculator!$B$2, -Calculator!$C$17,-Calculator!$C$13)) -> 24011659 | U52: =IF(B52>=Calculator!$H$7,U51*(1+Calculator!$H$3)-F52,FV(Calculator!$H$1,B52+Calculator!$H$8-Calculator!$B$2, -Calculator!$D$17,-Calculator!$D$13)) -> 2293335.9 | V52: =IF(B52>=Calculator!$H$7,V51*(1+Calculator!$H$3)-G52,FV(Calculator!$H$1,B52+Calculator!$H$8-Calculator!$B$2, -Calculator!$E$17,-Calculator!$E$13)) -> 9628579.2 | W52: =IF(B52>=Calculator!$H$7,W51*(1+Calculator!$H$3)-H52,FV(Calculator!$H$1,B52+Calculator!$H$8-Calculator!$B$2, -Calculator!$F$17,-Calculator!$F$13))+P52 -> 11836797 | X52: =D52+E52+G52+H52 -> 1856490.5 | Y52: =Y51*(1+Calculator!$H$6) -> 170833.73 | Z52: =IF(X52>0,D52*0.15+F52+Y52,0) -> 281875.45 | AA52: =X52-Z52 -> 1574615.1 | AB52: =AA52*Calculator!$H$5 -> 314923.01 | AC52: =IF((X52+Z52)=0,0,AB52/(X52+Z52)*100) -> 14.727274 | AD52: =W52-W51 -> 1408945.3
A53: 2071 | B53: =A53-Calculator!$H$8 -> 98 | D53: =IF(D52=0,IF(B53>=Calculator!$H$10,Calculator!$H$11,0)*Calculator!$H$17,D52*(1+Calculator!$H$6)) -> 164157.3 | E53: =IF(B53>=Calculator!$H$9,T52*Calculator!$H$14,0) -> 960466.36 | F53: =IF(B53>=Calculator!$H$9,U52*Calculator!$H$14,0) -> 91733.437 | G53: =IF(B53>=Calculator!$H$7,V52*Calculator!$H$14,0) -> 385143.17 | H53: =IF(B53>=Calculator!$H$7,IF(W52<=0,0,W52*Calculator!$H$14),0) -> 473471.88 | I53: =IF(I52=0,IF(B53>=Calculator!$H$7,Calculator!$H$12,0),I52*(1+Calculator!$H$6)) -> 0 | J53: =(D53*0.85+E53+H53+I53)*(1-Calculator!$H$5)+D53*0.15+(G53)*(1-Calculator!$H$4)+F53 -> 1721763.4 | K53: =D53+E53+F53+G53+H53+I53 -> 2074972.1 | L53: =K53-AB53 -> 1737129.2 | M53: =IF(B53=Calculator!$C$2,Calculator!$B$8,M52*(1+Calculator!$H$6)) -> 771035.19 | O53: =M53+N53 -> 771035.19 | P53: =L53-O53 -> 966094.04 | Q53: =IF(Calculator!$H$18="Y",Q52+IF(Q52<0,Q52*Calculator!$H$2,Q52*Calculator!$H$3)+P53,0) -> 0 | R53: =T53+U53+V53+W53 -> 51124984 | S53: =Q53+R53 -> 51124984 | T53: =IF(B53>=Calculator!$H$7,T52*(1+Calculator!$H$3)-E53,FV(Calculator!$H$1,B53+Calculator!$H$8-Calculator!$B$2, -Calculator!$C$17,-Calculator!$C$13)) -> 25212242 | U53: =IF(B53>=Calculator!$H$7,U52*(1+Calculator!$H$3)-F53,FV(Calculator!$H$1,B53+Calculator!$H$8-Calculator!$B$2, -Calculator!$D$17,-Calculator!$D$13)) -> 2408002.7 | V53: =IF(B53>=Calculator!$H$7,V52*(1+Calculator!$H$3)-G53,FV(Calculator!$H$1,B53+Calculator!$H$8-Calculator!$B$2, -Calculator!$E$17,-Calculator!$E$13)) -> 10110008 | W53: =IF(B53>=Calculator!$H$7,W52*(1+Calculator!$H$3)-H53,FV(Calculator!$H$1,B53+Calculator!$H$8-Calculator!$B$2, -Calculator!$F$17,-Calculator!$F$13))+P53 -> 13394731 | X53: =D53+E53+G53+H53 -> 1983238.7 | Y53: =Y52*(1+Calculator!$H$6) -> 177667.08 | Z53: =IF(X53>0,D53*0.15+F53+Y53,0) -> 294024.12 | AA53: =X53-Z53 -> 1689214.6 | AB53: =AA53*Calculator!$H$5 -> 337842.92 | AC53: =IF((X53+Z53)=0,0,AB53/(X53+Z53)*100) -> 14.835482 | AD53: =W53-W52 -> 1557933.9
A54: 2072 | B54: =A54-Calculator!$H$8 -> 99 | D54: =IF(D53=0,IF(B54>=Calculator!$H$10,Calculator!$H$11,0)*Calculator!$H$17,D53*(1+Calculator!$H$6)) -> 170723.59 | E54: =IF(B54>=Calculator!$H$9,T53*Calculator!$H$14,0) -> 1008489.7 | F54: =IF(B54>=Calculator!$H$9,U53*Calculator!$H$14,0) -> 96320.109 | G54: =IF(B54>=Calculator!$H$7,V53*Calculator!$H$14,0) -> 404400.33 | H54: =IF(B54>=Calculator!$H$7,IF(W53<=0,0,W53*Calculator!$H$14),0) -> 535789.24 | I54: =IF(I53=0,IF(B54>=Calculator!$H$7,Calculator!$H$12,0),I53*(1+Calculator!$H$6)) -> 0 | J54: =(D54*0.85+E54+H54+I54)*(1-Calculator!$H$5)+D54*0.15+(G54)*(1-Calculator!$H$4)+F54 -> 1837404.1 | K54: =D54+E54+F54+G54+H54+I54 -> 2215722.9 | L54: =K54-AB54 -> 1853182.9 | M54: =IF(B54=Calculator!$C$2,Calculator!$B$8,M53*(1+Calculator!$H$6)) -> 801876.6 | O54: =M54+N54 -> 801876.6 | P54: =L54-O54 -> 1051306.3 | Q54: =IF(Calculator!$H$18="Y",Q53+IF(Q53<0,Q53*Calculator!$H$2,Q53*Calculator!$H$3)+P54,0) -> 0 | R54: =T54+U54+V54+W54 -> 54732539 | S54: =Q54+R54 -> 54732539 | T54: =IF(B54>=Calculator!$H$7,T53*(1+Calculator!$H$3)-E54,FV(Calculator!$H$1,B54+Calculator!$H$8-Calculator!$B$2, -Calculator!$C$17,-Calculator!$C$13)) -> 26472854 | U54: =IF(B54>=Calculator!$H$7,U53*(1+Calculator!$H$3)-F54,FV(Calculator!$H$1,B54+Calculator!$H$8-Calculator!$B$2, -Calculator!$D$17,-Calculator!$D$13)) -> 2528402.9 | V54: =IF(B54>=Calculator!$H$7,V53*(1+Calculator!$H$3)-G54,FV(Calculator!$H$1,B54+Calculator!$H$8-Calculator!$B$2, -Calculator!$E$17,-Calculator!$E$13)) -> 10615509 | W54: =IF(B54>=Calculator!$H$7,W53*(1+Calculator!$H$3)-H54,FV(Calculator!$H$1,B54+Calculator!$H$8-Calculator!$B$2, -Calculator!$F$17,-Calculator!$F$13))+P54 -> 15115774 | X54: =D54+E54+G54+H54 -> 2119402.8 | Y54: =Y53*(1+Calculator!$H$6) -> 184773.77 | Z54: =IF(X54>0,D54*0.15+F54+Y54,0) -> 306702.41 | AA54: =X54-Z54 -> 1812700.4 | AB54: =AA54*Calculator!$H$5 -> 362540.08 | AC54: =IF((X54+Z54)=0,0,AB54/(X54+Z54)*100) -> 14.943296 | AD54: =W54-W53 -> 1721042.8
A55: 2073 | B55: =A55-Calculator!$H$8 -> 100 | D55: =IF(D54=0,IF(B55>=Calculator!$H$10,Calculator!$H$11,0)*Calculator!$H$17,D54*(1+Calculator!$H$6)) -> 177552.54 | E55: =IF(B55>=Calculator!$H$9,T54*Calculator!$H$14,0) -> 1058914.2 | F55: =IF(B55>=Calculator!$H$9,U54*Calculator!$H$14,0) -> 101136.11 | G55: =IF(B55>=Calculator!$H$7,V54*Calculator!$H$14,0) -> 424620.34 | H55: =IF(B55>=Calculator!$H$7,IF(W54<=0,0,W54*Calculator!$H$14),0) -> 604630.95 | I55: =IF(I54=0,IF(B55>=Calculator!$H$7,Calculator!$H$12,0),I54*(1+Calculator!$H$6)) -> 0 | J55: =(D55*0.85+E55+H55+I55)*(1-Calculator!$H$5)+D55*0.15+(G55)*(1-Calculator!$H$4)+F55 -> 1961499.1 | K55: =D55+E55+F55+G55+H55+I55 -> 2366854.1 | L55: =K55-AB55 -> 1977697.2 | M55: =IF(B55=Calculator!$C$2,Calculator!$B$8,M54*(1+Calculator!$H$6)) -> 833951.66 | O55: =M55+N55 -> 833951.66 | P55: =L55-O55 -> 1143745.6 | Q55: =IF(Calculator!$H$18="Y",Q54+IF(Q54<0,Q54*Calculator!$H$2,Q54*Calculator!$H$3)+P55,0) -> 0 | R55: =T55+U55+V55+W55 -> 58612912 | S55: =Q55+R55 -> 58612912 | T55: =IF(B55>=Calculator!$H$7,T54*(1+Calculator!$H$3)-E55,FV(Calculator!$H$1,B55+Calculator!$H$8-Calculator!$B$2, -Calculator!$C$17,-Calculator!$C$13)) -> 27796497 | U55: =IF(B55>=Calculator!$H$7,U54*(1+Calculator!$H$3)-F55,FV(Calculator!$H$1,B55+Calculator!$H$8-Calculator!$B$2, -Calculator!$D$17,-Calculator!$D$13)) -> 2654823 | V55: =IF(B55>=Calculator!$H$7,V54*(1+Calculator!$H$3)-G55,FV(Calculator!$H$1,B55+Calculator!$H$8-Calculator!$B$2, -Calculator!$E$17,-Calculator!$E$13)) -> 11146284 | W55: =IF(B55>=Calculator!$H$7,W54*(1+Calculator!$H$3)-H55,FV(Calculator!$H$1,B55+Calculator!$H$8-Calculator!$B$2, -Calculator!$F$17,-Calculator!$F$13))+P55 -> 17015308 | X55: =D55+E55+G55+H55 -> 2265718 | Y55: =Y54*(1+Calculator!$H$6) -> 192164.72 | Z55: =IF(X55>0,D55*0.15+F55+Y55,0) -> 319933.71 | AA55: =X55-Z55 -> 1945784.3 | AB55: =AA55*Calculator!$H$5 -> 389156.86 | AC55: =IF((X55+Z55)=0,0,AB55/(X55+Z55)*100) -> 15.050629 | AD55: =W55-W54 -> 1899534.3
A56: 2074 | B56: =A56-Calculator!$H$8 -> 101 | D56: =IF(D55=0,IF(B56>=Calculator!$H$10,Calculator!$H$11,0)*Calculator!$H$17,D55*(1+Calculator!$H$6)) -> 184654.64 | E56: =IF(B56>=Calculator!$H$9,T55*Calculator!$H$14,0) -> 1111859.9 | F56: =IF(B56>=Calculator!$H$9,U55*Calculator!$H$14,0) -> 106192.92 | G56: =IF(B56>=Calculator!$H$7,V55*Calculator!$H$14,0) -> 445851.36 | H56: =IF(B56>=Calculator!$H$7,IF(W55<=0,0,W55*Calculator!$H$14),0) -> 680612.32 | I56: =IF(I55=0,IF(B56>=Calculator!$H$7,Calculator!$H$12,0),I55*(1+Calculator!$H$6)) -> 0 | J56: =(D56*0.85+E56+H56+I56)*(1-Calculator!$H$5)+D56*0.15+(G56)*(1-Calculator!$H$4)+F56 -> 2094700.2 | K56: =D56+E56+F56+G56+H56+I56 -> 2529171.1 | L56: =K56-AB56 -> 2111324 | M56: =IF(B56=Calculator!$C$2,Calculator!$B$8,M55*(1+Calculator!$H$6)) -> 867309.73 | O56: =M56+N56 -> 867309.73 | P56: =L56-O56 -> 1244014.2 | Q56: =IF(Calculator!$H$18="Y",Q55+IF(Q55<0,Q55*Calculator!$H$2,Q55*Calculator!$H$3)+P56,0) -> 0 | R56: =T56+U56+V56+W56 -> 62787572 | S56: =Q56+R56 -> 62787572 | T56: =IF(B56>=Calculator!$H$7,T55*(1+Calculator!$H$3)-E56,FV(Calculator!$H$1,B56+Calculator!$H$8-Calculator!$B$2, -Calculator!$C$17,-Calculator!$C$13)) -> 29186321 | U56: =IF(B56>=Calculator!$H$7,U55*(1+Calculator!$H$3)-F56,FV(Calculator!$H$1,B56+Calculator!$H$8-Calculator!$B$2, -Calculator!$D$17,-Calculator!$D$13)) -> 2787564.1 | V56: =IF(B56>=Calculator!$H$7,V55*(1+Calculator!$H$3)-G56,FV(Calculator!$H$1,B56+Calculator!$H$8-Calculator!$B$2, -Calculator!$E$17,-Calculator!$E$13)) -> 11703598 | W56: =IF(B56>=Calculator!$H$7,W55*(1+Calculator!$H$3)-H56,FV(Calculator!$H$1,B56+Calculator!$H$8-Calculator!$B$2, -Calculator!$F$17,-Calculator!$F$13))+P56 -> 19110088 | X56: =D56+E56+G56+H56 -> 2422978.2 | Y56: =Y55*(1+Calculator!$H$6) -> 199851.31 | Z56: =IF(X56>0,D56*0.15+F56+Y56,0) -> 333742.42 | AA56: =X56-Z56 -> 2089235.8 | AB56: =AA56*Calculator!$H$5 -> 417847.15 | AC56: =IF((X56+Z56)=0,0,AB56/(X56+Z56)*100) -> 15.157399 | AD56: =W56-W55 -> 2094779.6
A57: 2075 | B57: =A57-Calculator!$H$8 -> 102 | D57: =IF(D56=0,IF(B57>=Calculator!$H$10,Calculator!$H$11,0)*Calculator!$H$17,D56*(1+Calculator!$H$6)) -> 192040.83 | E57: =IF(B57>=Calculator!$H$9,T56*Calculator!$H$14,0) -> 1167452.9 | F57: =IF(B57>=Calculator!$H$9,U56*Calculator!$H$14,0) -> 111502.57 | G57: =IF(B57>=Calculator!$H$7,V56*Calculator!$H$14,0) -> 468143.93 | H57: =IF(B57>=Calculator!$H$7,IF(W56<=0,0,W56*Calculator!$H$14),0) -> 764403.51 | I57: =IF(I56=0,IF(B57>=Calculator!$H$7,Calculator!$H$12,0),I56*(1+Calculator!$H$6)) -> 0 | J57: =(D57*0.85+E57+H57+I57)*(1-Calculator!$H$5)+D57*0.15+(G57)*(1-Calculator!$H$4)+F57 -> 2237711.1 | K57: =D57+E57+F57+G57+H57+I57 -> 2703543.7 | L57: =K57-AB57 -> 2254766.3 | M57: =IF(B57=Calculator!$C$2,Calculator!$B$8,M56*(1+Calculator!$H$6)) -> 902002.12 | O57: =M57+N57 -> 902002.12 | P57: =L57-O57 -> 1352764.2 | Q57: =IF(Calculator!$H$18="Y",Q56+IF(Q56<0,Q56*Calculator!$H$2,Q56*Calculator!$H$3)+P57,0) -> 0 | R57: =T57+U57+V57+W57 -> 67279714 | S57: =Q57+R57 -> 67279714 | T57: =IF(B57>=Calculator!$H$7,T56*(1+Calculator!$H$3)-E57,FV(Calculator!$H$1,B57+Calculator!$H$8-Calculator!$B$2, -Calculator!$C$17,-Calculator!$C$13)) -> 30645638 | U57: =IF(B57>=Calculator!$H$7,U56*(1+Calculator!$H$3)-F57,FV(Calculator!$H$1,B57+Calculator!$H$8-Calculator!$B$2, -Calculator!$D$17,-Calculator!$D$13)) -> 2926942.4 | V57: =IF(B57>=Calculator!$H$7,V56*(1+Calculator!$H$3)-G57,FV(Calculator!$H$1,B57+Calculator!$H$8-Calculator!$B$2, -Calculator!$E$17,-Calculator!$E$13)) -> 12288778 | W57: =IF(B57>=Calculator!$H$7,W56*(1+Calculator!$H$3)-H57,FV(Calculator!$H$1,B57+Calculator!$H$8-Calculator!$B$2, -Calculator!$F$17,-Calculator!$F$13))+P57 -> 21418356 | X57: =D57+E57+G57+H57 -> 2592041.1 | Y57: =Y56*(1+Calculator!$H$6) -> 207845.36 | Z57: =IF(X57>0,D57*0.15+F57+Y57,0) -> 348154.05 | AA57: =X57-Z57 -> 2243887.1 | AB57: =AA57*Calculator!$H$5 -> 448777.41 | AC57: =IF((X57+Z57)=0,0,AB57/(X57+Z57)*100) -> 15.263525 | AD57: =W57-W56 -> 2308268.5
A58: 2076 | B58: =A58-Calculator!$H$8 -> 103 | D58: =IF(D57=0,IF(B58>=Calculator!$H$10,Calculator!$H$11,0)*Calculator!$H$17,D57*(1+Calculator!$H$6)) -> 199722.46 | E58: =IF(B58>=Calculator!$H$9,T57*Calculator!$H$14,0) -> 1225825.5 | F58: =IF(B58>=Calculator!$H$9,U57*Calculator!$H$14,0) -> 117077.69 | G58: =IF(B58>=Calculator!$H$7,V57*Calculator!$H$14,0) -> 491551.13 | H58: =IF(B58>=Calculator!$H$7,IF(W57<=0,0,W57*Calculator!$H$14),0) -> 856734.25 | I58: =IF(I57=0,IF(B58>=Calculator!$H$7,Calculator!$H$12,0),I57*(1+Calculator!$H$6)) -> 0 | J58: =(D58*0.85+E58+H58+I58)*(1-Calculator!$H$5)+D58*0.15+(G58)*(1-Calculator!$H$4)+F58 -> 2391291.1 | K58: =D58+E58+F58+G58+H58+I58 -> 2890911 | L58: =K58-AB58 -> 2408783.4 | M58: =IF(B58=Calculator!$C$2,Calculator!$B$8,M57*(1+Calculator!$H$6)) -> 938082.2 | O58: =M58+N58 -> 938082.2 | P58: =L58-O58 -> 1470701.2 | Q58: =IF(Calculator!$H$18="Y",Q57+IF(Q57<0,Q57*Calculator!$H$2,Q57*Calculator!$H$3)+P58,0) -> 0 | R58: =T58+U58+V58+W58 -> 72114401 | S58: =Q58+R58 -> 72114401 | T58: =IF(B58>=Calculator!$H$7,T57*(1+Calculator!$H$3)-E58,FV(Calculator!$H$1,B58+Calculator!$H$8-Calculator!$B$2, -Calculator!$C$17,-Calculator!$C$13)) -> 32177919 | U58: =IF(B58>=Calculator!$H$7,U57*(1+Calculator!$H$3)-F58,FV(Calculator!$H$1,B58+Calculator!$H$8-Calculator!$B$2, -Calculator!$D$17,-Calculator!$D$13)) -> 3073289.5 | V58: =IF(B58>=Calculator!$H$7,V57*(1+Calculator!$H$3)-G58,FV(Calculator!$H$1,B58+Calculator!$H$8-Calculator!$B$2, -Calculator!$E$17,-Calculator!$E$13)) -> 12903217 | W58: =IF(B58>=Calculator!$H$7,W57*(1+Calculator!$H$3)-H58,FV(Calculator!$H$1,B58+Calculator!$H$8-Calculator!$B$2, -Calculator!$F$17,-Calculator!$F$13))+P58 -> 23959975 | X58: =D58+E58+G58+H58 -> 2773833.3 | Y58: =Y57*(1+Calculator!$H$6) -> 216159.17 | Z58: =IF(X58>0,D58*0.15+F58+Y58,0) -> 363195.24 | AA58: =X58-Z58 -> 2410638.1 | AB58: =AA58*Calculator!$H$5 -> 482127.62 | AC58: =IF((X58+Z58)=0,0,AB58/(X58+Z58)*100) -> 15.368927 | AD58: =W58-W57 -> 2541619
A59: 2077 | B59: =A59-Calculator!$H$8 -> 104 | D59: =IF(D58=0,IF(B59>=Calculator!$H$10,Calculator!$H$11,0)*Calculator!$H$17,D58*(1+Calculator!$H$6)) -> 207711.36 | E59: =IF(B59>=Calculator!$H$9,T58*Calculator!$H$14,0) -> 1287116.8 | F59: =IF(B59>=Calculator!$H$9,U58*Calculator!$H$14,0) -> 122931.58 | G59: =IF(B59>=Calculator!$H$7,V58*Calculator!$H$14,0) -> 516128.68 | H59: =IF(B59>=Calculator!$H$7,IF(W58<=0,0,W58*Calculator!$H$14),0) -> 958399.01 | I59: =IF(I58=0,IF(B59>=Calculator!$H$7,Calculator!$H$12,0),I58*(1+Calculator!$H$6)) -> 0 | J59: =(D59*0.85+E59+H59+I59)*(1-Calculator!$H$5)+D59*0.15+(G59)*(1-Calculator!$H$4)+F59 -> 2556260.4 | K59: =D59+E59+F59+G59+H59+I59 -> 3092287.4 | L59: =K59-AB59 -> 2574195 | M59: =IF(B59=Calculator!$C$2,Calculator!$B$8,M58*(1+Calculator!$H$6)) -> 975605.49 | O59: =M59+N59 -> 975605.49 | P59: =L59-O59 -> 1598589.5 | Q59: =IF(Calculator!$H$18="Y",Q58+IF(Q58<0,Q58*Calculator!$H$2,Q58*Calculator!$H$3)+P59,0) -> 0 | R59: =T59+U59+V59+W59 -> 77318711 | S59: =Q59+R59 -> 77318711 | T59: =IF(B59>=Calculator!$H$7,T58*(1+Calculator!$H$3)-E59,FV(Calculator!$H$1,B59+Calculator!$H$8-Calculator!$B$2, -Calculator!$C$17,-Calculator!$C$13)) -> 33786815 | U59: =IF(B59>=Calculator!$H$7,U58*(1+Calculator!$H$3)-F59,FV(Calculator!$H$1,B59+Calculator!$H$8-Calculator!$B$2, -Calculator!$D$17,-Calculator!$D$13)) -> 3226954 | V59: =IF(B59>=Calculator!$H$7,V58*(1+Calculator!$H$3)-G59,FV(Calculator!$H$1,B59+Calculator!$H$8-Calculator!$B$2, -Calculator!$E$17,-Calculator!$E$13)) -> 13548378 | W59: =IF(B59>=Calculator!$H$7,W58*(1+Calculator!$H$3)-H59,FV(Calculator!$H$1,B59+Calculator!$H$8-Calculator!$B$2, -Calculator!$F$17,-Calculator!$F$13))+P59 -> 26756564 | X59: =D59+E59+G59+H59 -> 2969355.8 | Y59: =Y58*(1+Calculator!$H$6) -> 224805.54 | Z59: =IF(X59>0,D59*0.15+F59+Y59,0) -> 378893.82 | AA59: =X59-Z59 -> 2590462 | AB59: =AA59*Calculator!$H$5 -> 518092.4 | AC59: =IF((X59+Z59)=0,0,AB59/(X59+Z59)*100) -> 15.47353 | AD59: =W59-W58 -> 2796588.3
A60: 2078 | B60: =A60-Calculator!$H$8 -> 105 | D60: =IF(D59=0,IF(B60>=Calculator!$H$10,Calculator!$H$11,0)*Calculator!$H$17,D59*(1+Calculator!$H$6)) -> 216019.81 | E60: =IF(B60>=Calculator!$H$9,T59*Calculator!$H$14,0) -> 1351472.6 | F60: =IF(B60>=Calculator!$H$9,U59*Calculator!$H$14,0) -> 129078.16 | G60: =IF(B60>=Calculator!$H$7,V59*Calculator!$H$14,0) -> 541935.12 | H60: =IF(B60>=Calculator!$H$7,IF(W59<=0,0,W59*Calculator!$H$14),0) -> 1070262.5 | I60: =IF(I59=0,IF(B60>=Calculator!$H$7,Calculator!$H$12,0),I59*(1+Calculator!$H$6)) -> 0 | J60: =(D60*0.85+E60+H60+I60)*(1-Calculator!$H$5)+D60*0.15+(G60)*(1-Calculator!$H$4)+F60 -> 2733504.3 | K60: =D60+E60+F60+G60+H60+I60 -> 3308768.2 | L60: =K60-AB60 -> 2751886 | M60: =IF(B60=Calculator!$C$2,Calculator!$B$8,M59*(1+Calculator!$H$6)) -> 1014629.7 | O60: =M60+N60 -> 1014629.7 | P60: =L60-O60 -> 1737256.3 | Q60: =IF(Calculator!$H$18="Y",Q59+IF(Q59<0,Q59*Calculator!$H$2,Q59*Calculator!$H$3)+P60,0) -> 0 | R60: =T60+U60+V60+W60 -> 82921903 | S60: =Q60+R60 -> 82921903 | T60: =IF(B60>=Calculator!$H$7,T59*(1+Calculator!$H$3)-E60,FV(Calculator!$H$1,B60+Calculator!$H$8-Calculator!$B$2, -Calculator!$C$17,-Calculator!$C$13)) -> 35476156 | U60: =IF(B60>=Calculator!$H$7,U59*(1+Calculator!$H$3)-F60,FV(Calculator!$H$1,B60+Calculator!$H$8-Calculator!$B$2, -Calculator!$D$17,-Calculator!$D$13)) -> 3388301.6 | V60: =IF(B60>=Calculator!$H$7,V59*(1+Calculator!$H$3)-G60,FV(Calculator!$H$1,B60+Calculator!$H$8-Calculator!$B$2, -Calculator!$E$17,-Calculator!$E$13)) -> 14225797 | W60: =IF(B60>=Calculator!$H$7,W59*(1+Calculator!$H$3)-H60,FV(Calculator!$H$1,B60+Calculator!$H$8-Calculator!$B$2, -Calculator!$F$17,-Calculator!$F$13))+P60 -> 29831648 | X60: =D60+E60+G60+H60 -> 3179690.1 | Y60: =Y59*(1+Calculator!$H$6) -> 233797.76 | Z60: =IF(X60>0,D60*0.15+F60+Y60,0) -> 395278.89 | AA60: =X60-Z60 -> 2784411.2 | AB60: =AA60*Calculator!$H$5 -> 556882.24 | AC60: =IF((X60+Z60)=0,0,AB60/(X60+Z60)*100) -> 15.577261 | AD60: =W60-W59 -> 3075084.5
... A88: 2106 | B88: =A88-Calculator!$H$8 -> 133 | D88: =IF(D87=0,IF(B88>=Calculator!$H$10,Calculator!$H$11,0)*Calculator!$H$17,D87*(1+Calculator!$H$6)) -> 647779.32 | E88: =IF(B88>=Calculator!$H$9,T87*Calculator!$H$14,0) -> 5297947.2 | F88: =IF(B88>=Calculator!$H$9,U87*Calculator!$H$14,0) -> 506003.05 | G88: =IF(B88>=Calculator!$H$7,V87*Calculator!$H$14,0) -> 2124455.6 | H88: =IF(B88>=Calculator!$H$7,IF(W87<=0,0,W87*Calculator!$H$14),0) -> 15933535 | I88: =IF(I87=0,IF(B88>=Calculator!$H$7,Calculator!$H$12,0),I87*(1+Calculator!$H$6)) -> 0 | J88: =(D88*0.85+E88+H88+I88)*(1-Calculator!$H$5)+D88*0.15+(G88)*(1-Calculator!$H$4)+F88 -> 19940856 | K88: =D88+E88+F88+G88+H88+I88 -> 24509720 | L88: =K88-AB88 -> 19969829 | M88: =IF(B88=Calculator!$C$2,Calculator!$B$8,M87*(1+Calculator!$H$6)) -> 3042573.5 | O88: =M88+N88 -> 3042573.5 | P88: =L88-O88 -> 16927255 | Q88: =IF(Calculator!$H$18="Y",Q87+IF(Q87<0,Q87*Calculator!$H$2,Q87*Calculator!$H$3)+P88,0) -> 0 | R88: =T88+U88+V88+W88 -> 6.433032e+08 | S88: =Q88+R88 -> 6.433032e+08 | T88: =IF(B88>=Calculator!$H$7,T87*(1+Calculator!$H$3)-E88,FV(Calculator!$H$1,B88+Calculator!$H$8-Calculator!$B$2, -Calculator!$C$17,-Calculator!$C$13)) -> 1.3907111e+08 | U88: =IF(B88>=Calculator!$H$7,U87*(1+Calculator!$H$3)-F88,FV(Calculator!$H$1,B88+Calculator!$H$8-Calculator!$B$2, -Calculator!$D$17,-Calculator!$D$13)) -> 13282580 | V88: =IF(B88>=Calculator!$H$7,V87*(1+Calculator!$H$3)-G88,FV(Calculator!$H$1,B88+Calculator!$H$8-Calculator!$B$2, -Calculator!$E$17,-Calculator!$E$13)) -> 55766961 | W88: =IF(B88>=Calculator!$H$7,W87*(1+Calculator!$H$3)-H88,FV(Calculator!$H$1,B88+Calculator!$H$8-Calculator!$B$2, -Calculator!$F$17,-Calculator!$F$13))+P88 -> 4.3518255e+08 | X88: =D88+E88+G88+H88 -> 24003717 | Y88: =Y87*(1+Calculator!$H$6) -> 701090.12 | Z88: =IF(X88>0,D88*0.15+F88+Y88,0) -> 1304260.1 | AA88: =X88-Z88 -> 22699457 | AB88: =AA88*Calculator!$H$5 -> 4539891.4 | AC88: =IF((X88+Z88)=0,0,AB88/(X88+Z88)*100) -> 17.938579 | AD88: =W88-W87 -> 36844174

Sheet Expenses
A1: Expense | B1: Retire after 65 | C1: Retire before 65
A2: Rent / Taxes-Maint | B2: 3000 | C2: 4000
A3: Groceries | B3: 800 | C3: 1000
A4: Dining out / Entertainment | B4: 500 | C4: 500
A5: Utilities | B5: 500 | C5: 500
A6: Medical | B6: 2500 | C6: 2500
A7: Travel | B7: 1500 | C7: 1500
A8: Additional | B8: 500 | C8: 1000
A12: Total | B12: =SUM(B2:B10) -> 9300 | C12: =SUM(C2:C10) -> 11000
A15: Estimated monthly expenses in today's dollars

Sheet Accounts
A1: Account Name | B1: Owner | C1: Balance
A2: IRA | B2: Siva | C2: 1080000
A3: 401k | B3: Siva | C3: 256000
A4: Roth IRA | B4: Siva | C4: 66000
A5: HSA | B5: Siva | C5: 38000
A6: IRA | B6: Shireesha | C6: 0
A7: 401k | B7: Shireesha | C7: 388000
A8: Roth IRA | B8: Shireesha | C8: 44000
A9: HSA | B9: Shireesha | C9: 20000
A10: Taxable | B10: Siva | C10: 780000
A11: ESPP | B11: Shireesha | C11: 93000
A12: Pension 1 | B12: Siva | C12: 91000
A13: Pension 2 | B13: Siva | C13: 53000
... A20: Ohio Lands (2) | B20: Siva | C20: 40000
A23: Pre-tax total | C23: =SUM(C2,C3,C6,C7,C12,C13) -> 1868000
A24: After-tax total | C24: =SUM(C4,C8,C9,C5) -> 168000
A25: Taxable Total | C25: =SUM(C10,C11) -> 873000
A26: Assets total | C26: =SUM(C15:C20) -> 426000
A28: Total | C28: =C23+C24+C25+C26 -> 3335000

Sheet Other Income
A1: Income Sources | B1: Amount - Annual
A2: Pension
A3: Options Income | B3: 50000
A4: Rental Income | B4: 0
A7: Total | B7: =SUM(B2:B4) -> 50000

Sheet Compounding
A1: Age | B1: Networth
A2: 50 | B2: 1000000
A3: 55 | B3: =B2*2 -> 2000000
A4: 60 | B4: =B3*2 -> 4000000
A5: 65 | B5: =B4*2 -> 8000000
A6: 70 | B6: =B5*2 -> 16000000
A7: 75 | B7: =B6*2 -> 32000000
A8: 80 | B8: =B7*2 -> 64000000
A9: 85 | B9: =B8*2 -> 128000000
A10: 90 | B10: =B9*2 -> 256000000
A11: 95 | B11: =B10*2 -> 512000000
A12: 100 | B12: =B11*2 -> 1024000000

Sheet Defaults
A1: Growth rate (return) before retirement | B1: 0.1
A2: Loan rate (if borrowed for expenses) | B2: 0.1
A3: Growth rate (return) during retirement | B3: 0.05
A4: Capital gains & gividends blended tax rate | B4: 0.2
A5: Tax rate during retirement | B5: 0.25
A6: Inflation | B6: 0.04
A7: Retirement age | B7: 65
A8: Birth year | B8: 1973
A9: Retirement distributions start age | B9: 65
A10: Social security benefit start age | B10: 67
A11: Estimated SS income - annual | B11: 30000
A12: Other recurring income at start of retirement - annual | B12: 0
... A15: Age of asset transfer to kids | B15: 80
A16: Total money borrowed for special expenses | B16: =SUM(Details!E4:E88) -> 108248607
A17: Contribution multiplier (number of earners) | B17: 1
A19: Work in progress
